Workbook

Sheet DASHBOARD
A1: DSIC RESEARCH GROUP — DASHBOARD BIMBINGAN TUGAS AKHIR
A2: Monitoring mahasiswa, akun, penetapan topik, logbook 14 pertemuan, dan ketercapaian artefak penelitian.
A4: Total Mahasiswa | C4: 7 | D4: Topik Disetujui | F4: =COUNTIF(H7:H13,"Disetujui") -> 6 | G4: Pertemuan Selesai | I4: =SUM(I7:I13) -> 9 | J4: Total Target Pertemuan | L4: 98
A6: NIM | B6: Nama | C6: Email | D6: GitHub | E6: Sumber Topik | F6: Kode | G6: Judul Final | H6: Status Topik | I6: Pertemuan Selesai | J6: Terverifikasi | K6: Pertemuan Terakhir | L6: Sheet
A7: 123450063 | B7: ARYA MUDA SIREGAR | C7: arya.123450063@student.itera.ac.id | D7: =HYPERLINK("https://github.com/Aryamuda","@Aryamuda") -> @Aryamuda | E7: ='123450063'!C5 -> Katalog DSIC | F7: ='123450063'!C6 -> DSIC30-07 | G7: ='123450063'!C18 -> LLM yang Hanya Boleh Memakai Data Tepercaya | H7: ='123450063'!G5 -> Disetujui | I7: =COUNTIF('123450063'!L25:L38,"Selesai") -> 1 | J7: =COUNTIF('123450063'!M25:M38,TRUE) -> 1 | K7: =IFERROR(MAX('123450063'!E25:E38),"") -> 46269 | L7: Buka
A8: 123450114 | B8: Desman Velius Halawa | C8: desmanhalawa2020@gmail.com | D8: =HYPERLINK("https://github.com/desmanveliushalawa","@desmanveliushalawa") -> @desmanveliushalawa | E8: ='123450114'!C5 -> Katalog DSIC | F8: ='123450114'!C6 -> DSIC26-04 | G8: ='123450114'!C18 -> Ukuran Berkas Parquet yang Pas untuk Lakehouse Kecil | H8: ='123450114'!G5 -> Disetujui | I8: =COUNTIF('123450114'!L25:L38,"Selesai") -> 2 | J8: =COUNTIF('123450114'!M25:M38,TRUE) -> 2 | K8: =IFERROR(MAX('123450114'!E25:E38),"") -> 46273 | L8: Buka
A9: 123450104 | B9: Fabio Banyu Cyto | C9: fabio.123450104@student.itera.ac.id | D9: =HYPERLINK("https://github.com/fabiobanyu","@fabiobanyu") -> @fabiobanyu | E9: ='123450104'!C5 -> Katalog DSIC | F9: ='123450104'!C6 -> DSIC27-06 | G9: ='123450104'!C18 -> Mencari Audio yang Mirip Ketika Datanya Terbatas | H9: ='123450104'!G5 -> Disetujui | I9: =COUNTIF('123450104'!L25:L38,"Selesai") -> 2 | J9: =COUNTIF('123450104'!M25:M38,TRUE) -> 2 | K9: =IFERROR(MAX('123450104'!E25:E38),"") -> 46272 | L9: Buka
A10: 123450039 | B10: FEBY ANGELINA | C10: feby.123450039@student.itera.ac.id | D10: =HYPERLINK("https://github.com/FebyAngelina","@FebyAngelina") -> @FebyAngelina | E10: ='123450039'!C5 -> Katalog DSIC | F10: ='123450039'!C6 -> DSIC29-06 | G10: ='123450039'!C18 -> Haruskah Query pada Data Meragukan Diperlakukan Berbeda? | H10: ='123450039'!G5 -> Disetujui | I10: =COUNTIF('123450039'!L25:L38,"Selesai") -> 1 | J10: =COUNTIF('123450039'!M25:M38,TRUE) -> 1 | K10: =IFERROR(MAX('123450039'!E25:E38),"") -> 46271 | L10: Buka
A11: 123450115 | B11: MUHAMMAD FADIL ALFAIZI | C11: muhammad.123450115@student.itera.ac.id | D11: =HYPERLINK("https://github.com/FadilAlfaizii","@FadilAlfaizii") -> @FadilAlfaizii | E11: ='123450115'!C5 -> Katalog DSIC | F11: ='123450115'!C6 -> DSIC29-07 | G11: ='123450115'!C18 -> Memilih Konfigurasi Sumber Daya Berdasarkan Jenis Beban | H11: ='123450115'!G5 -> Disetujui | I11: =COUNTIF('123450115'!L25:L38,"Selesai") -> 2 | J11: =COUNTIF('123450115'!M25:M38,TRUE) -> 2 | K11: =IFERROR(MAX('123450115'!E25:E38),"") -> 46277 | L11: Buka
A12: 123450003 | B12: Rahma Oktavia Albar | C12: rahma.123450003@student.itera.ac.id | D12: =HYPERLINK("https://github.com/Rahmaoktaviaalbar003","@Rahmaoktaviaalbar003") -> @Rahmaoktaviaalbar003 | E12: ='123450003'!C5 -> Usulan Mahasiswa | F12: ='123450003'!C6 | G12: ='123450003'!C18 -> Ide 1 (Utama) : Pengembangan Sistem Pendukung Keputusan dan Rekomendasi Pemilihan Supplier Green Bean Kopi atau Komoditas Lain Melalui Metode Pengambilan Keputusan Multikriteria. | H12: ='123450003'!G5 | I12: =COUNTIF('123450003'!L25:L38,"Selesai") -> 0 | J12: =COUNTIF('123450003'!M25:M38,TRUE) -> 0 | K12: =IFERROR(MAX('123450003'!E25:E38),"") -> 0 | L12: Buka
A13: 123450029 | B13: Vania Claresta | C13: vania.123450029@student.itera.ac.id | D13: =HYPERLINK("https://github.com/vaniaclrstaa","@vaniaclrstaa") -> @vaniaclrstaa | E13: ='123450029'!C5 -> Katalog DSIC | F13: ='123450029'!C6 -> DSIC26-06 | G13: ='123450029'!C18 -> Apa yang Terjadi Ketika Pipeline Gagal di Tengah Jalan? | H13: ='123450029'!G5 -> Disetujui | I13: =COUNTIF('123450029'!L25:L38,"Selesai") -> 1 | J13: =COUNTIF('123450029'!M25:M38,TRUE) -> 1 | K13: =IFERROR(MAX('123450029'!E25:E38),"") -> 46274 | L13: Buka

Sheet KATALOG_TOPIK
A1: KATALOG TOPIK TUGAS AKHIR — DSIC RESEARCH GROUP
A2: Topik 2026–2027 berstatus Dibuka; 2028–2030 merupakan peta jalan. Kolom O–Q membaca pilihan mahasiswa secara otomatis.
A3: Kode | B3: Tahun | C3: Status | D3: Judul | E3: Pertanyaan Penelitian | F3: Konsep Dasar | G3: Pembanding / Baseline | H3: Kebaruan | I3: Dataset | J3: Pekerjaan 4 Bulan | K3: Definisi Selesai | L3: Cocok Untuk | M3: Luaran | N3: Bacaan Inti | O3: Jumlah Dipilih | P3: Dipilih Oleh | Q3: Ketersediaan
A4: DSIC26-01 | B4: 2026 | C4: Dibuka | D4: Strategi Indeks yang Menyesuaikan Pola Pencarian | E4: Pada data yang sama dengan campuran pencarian nilai persis, rentang nilai, teks, dan lokasi, kapan B-tree, BRIN, GIN, atau kombinasinya memberi keseimbangan terbaik antara waktu pencarian dan ruang penyimpanan? | F4: Indeks bekerja seperti indeks di belakang buku: ia membantu menemukan bagian yang dicari tanpa membaca seluruh isi. Yang menarik, indeks tidak selalu menguntungkan — ia menambah ruang simpan dan memperlambat penulisan data. Pemilihan jalur akses adalah salah satu keputusan tertua sekaligus paling hidup di dunia basis data. | G4: Tanpa indeks sama sekali, lalu B-tree bawaan. | H4: Pilihan indeks diturunkan dari profil beban kerja yang benar-benar dijalankan, bukan dari benchmark umum. | I4: NYC TLC Trip Record Data sebagai data utama. Snapshot JADESTA/Sigerciv bisa dipakai sebagai contoh lokal. | J4: Tetapkan 3–4 pola pencarian yang mewakili beban kerja nyata. Jalankan semuanya tanpa indeks, lalu dengan tiap jenis indeks, lalu dengan kombinasi. Catat waktu eksekusi, jumlah baris yang dibaca, ukuran indeks, dan efeknya pada kecepatan menulis data. | K4: Ada tabel perbandingan yang konsisten untuk setiap pola pencarian, dan kamu bisa menjelaskan kapan sebuah indeks menolong serta kapan ia justru menjadi beban. | L4: Kamu senang SQL, betah membaca query plan, dan ingin hasil yang sangat terukur. | M4: Skripsi; berpeluang menjadi naskah artikel bila hasilnya kuat. | N4: Klasik 2, 3 · Terbaru 1, 3, 4, 5 | O4: =IF(AND('123450063'!$C$5="Katalog DSIC",'123450063'!$C$6=$A4),1,0)+IF(AND('1'!$C$5="Katalog DSIC",'1'!$C$6=$A4),1,0)+IF(AND('123450104'!$C$5="Katalog DSIC",'123450104'!$C$6=$A4),1,0)+IF(AND('123450039'!$C$5="Katalog DSIC",'123450039'!$C$6=$A4),1,0)+IF(AND('123450115'!$C$5="Katalog DSIC",'123450115'!$C$6=$A4),1,0)+IF(AND('123450003'!$C$5="Katalog DSIC",'123450003'!$C$6=$A4),1,0)+IF(AND('123450029'!$C$5="Katalog DSIC",'123450029'!$C$6=$A4),1,0) -> #REF! | P4: =TEXTJOIN(", ",TRUE,IF(AND('123450063'!$C$5="Katalog DSIC",'123450063'!$C$6=$A4),"ARYA MUDA SIREGAR",""),IF(AND('1'!$C$5="Katalog DSIC",'1'!$C$6=$A4),"Desman Velius Halawa",""),IF(AND('123450104'!$C$5="Katalog DSIC",'123450104'!$C$6=$A4),"Fabio Banyu Cyto",""),IF(AND('123450039'!$C$5="Katalog DSIC",'123450039'!$C$6=$A4),"FEBY ANGELINA",""),IF(AND('123450115'!$C$5="Katalog DSIC",'123450115'!$C$6=$A4),"MUHAMMAD FADIL ALFAIZI",""),IF(AND('123450003'!$C$5="Katalog DSIC",'123450003'!$C$6=$A4),"Rahma Oktavia Albar",""),IF(AND('123450029'!$C$5="Katalog DSIC",'123450029'!$C$6=$A4),"Vania Claresta","")) -> #REF! | Q4: =IF(C4<>"Dibuka","Peta Jalan",IF(O4=0,"Tersedia",IF(O4=1,"Dipilih","Dipilih >1"))) -> #REF!
A5: DSIC26-02 | B5: 2026 | C5: Dibuka | D5: Menyimpan Riwayat Perubahan Data dari Banyak Sumber | E5: Untuk data yang datang dari beberapa sumber dan kadang saling bertentangan, apakah menyimpan setiap perubahan sebagai catatan tersendiri membuat penelusuran jauh lebih mudah tanpa membuat pencarian kembali menjadi mahal, dibanding hanya menyimpan keadaan terakhir? | F5: Sebuah nilai tidak hanya penting karena isinya, tetapi juga karena kita perlu tahu dari mana ia berasal dan bagaimana ia berubah. Inilah yang disebut provenance atau asal-usul data. Format tabel modern juga menyimpan riwayat versi supaya keadaan lama tetap bisa dilihat kembali. | G5: Tabel yang hanya menyimpan keadaan terkini. | H5: Mengukur langsung pertukaran antara kemudahan audit, ukuran penyimpanan, dan waktu query pada data multisumber. | I5: Subset riwayat revisi Wikipedia/Wikimedia, atau beberapa snapshot data pariwisata publik yang diambil pada waktu berbeda. | J5: Bangun dua cara penyimpanan yang sederhana. Jalankan skenario perubahan yang sama pada keduanya. Bandingkan kemampuan menjawab pertanyaan seperti “kapan nilai ini berubah dan dari sumber mana”, waktu pencarian kembali, dan pertumbuhan ukuran data. | K5: Dua rancangan sudah diuji pada skenario identik, dan kamu bisa menunjukkan dengan angka di mana masing-masing unggul dan di mana ia kalah. | L5: Kamu tertarik pada sejarah perubahan data, audit, dan keandalan informasi. | M5: Skripsi; berpeluang menjadi naskah artikel bila hasilnya kuat. | N5: Klasik 4 · Terbaru 6, 7, 8 | O5: =IF(AND('123450063'!$C$5="Katalog DSIC",'123450063'!$C$6=$A5),1,0)+IF(AND('1'!$C$5="Katalog DSIC",'1'!$C$6=$A5),1,0)+IF(AND('123450104'!$C$5="Katalog DSIC",'123450104'!$C$6=$A5),1,0)+IF(AND('123450039'!$C$5="Katalog DSIC",'123450039'!$C$6=$A5),1,0)+IF(AND('123450115'!$C$5="Katalog DSIC",'123450115'!$C$6=$A5),1,0)+IF(AND('123450003'!$C$5="Katalog DSIC",'123450003'!$C$6=$A5),1,0)+IF(AND('123450029'!$C$5="Katalog DSIC",'123450029'!$C$6=$A5),1,0) -> #REF! | P5: =TEXTJOIN(", ",TRUE,IF(AND('123450063'!$C$5="Katalog DSIC",'123450063'!$C$6=$A5),"ARYA MUDA SIREGAR",""),IF(AND('1'!$C$5="Katalog DSIC",'1'!$C$6=$A5),"Desman Velius Halawa",""),IF(AND('123450104'!$C$5="Katalog DSIC",'123450104'!$C$6=$A5),"Fabio Banyu Cyto",""),IF(AND('123450039'!$C$5="Katalog DSIC",'123450039'!$C$6=$A5),"FEBY ANGELINA",""),IF(AND('123450115'!$C$5="Katalog DSIC",'123450115'!$C$6=$A5),"MUHAMMAD FADIL ALFAIZI",""),IF(AND('123450003'!$C$5="Katalog DSIC",'123450003'!$C$6=$A5),"Rahma Oktavia Albar",""),IF(AND('123450029'!$C$5="Katalog DSIC",'123450029'!$C$6=$A5),"Vania Claresta","")) -> #REF! | Q5: =IF(C5<>"Dibuka","Peta Jalan",IF(O5=0,"Tersedia",IF(O5=1,"Dipilih","Dipilih >1"))) -> #REF!
A6: DSIC26-03 | B6: 2026 | C6: Dibuka | D6: Gerbang Kualitas Data Berbasis Tingkat Keyakinan | E6: Apakah menggabungkan keandalan sumber, kebaruan, kelengkapan, dan tingkat konflik menghasilkan penyaringan data yang lebih baik daripada aturan pemeriksaan biasa? | F6: Kualitas data bukan hanya soal “benar”. Ia juga menyangkut kelengkapan, konsistensi, relevansi, dan kemudahan dipakai. Belakangan ini muncul pandangan bahwa memperbaiki data sering memberi hasil lebih besar daripada mengganti model. | G6: Aturan validasi sederhana: cek tipe, cek rentang, cek nilai kosong. | H6: Skor keyakinan gabungan dari beberapa dimensi, bukan aturan lolos/tidak lolos. | I6: Snapshot JADESTA/Sigerciv dari sumber publik, dengan kesalahan uji yang ditambahkan secara terkendali sehingga jawaban benarnya diketahui. | J6: Susun seperangkat aturan dasar. Bangun skor keyakinan multidimensi. Suntikkan empat sampai lima jenis kesalahan yang sudah ditentukan. Ukur berapa banyak kesalahan yang tertangkap dan berapa banyak data benar yang ikut tertandai. | K6: Ada angka ketepatan untuk setiap jenis kesalahan, dan kamu bisa menjelaskan jenis kesalahan mana yang paling mudah dan paling sulit ditemukan. | L6: Kamu suka bekerja dengan kebersihan data dan ingin topik yang sangat dekat dengan praktik data science sehari-hari. | M6: Skripsi; berpeluang menjadi naskah artikel bila hasilnya kuat. | N6: Klasik 5 · Terbaru 9, 10, 11 | O6: =IF(AND('123450063'!$C$5="Katalog DSIC",'123450063'!$C$6=$A6),1,0)+IF(AND('1'!$C$5="Katalog DSIC",'1'!$C$6=$A6),1,0)+IF(AND('123450104'!$C$5="Katalog DSIC",'123450104'!$C$6=$A6),1,0)+IF(AND('123450039'!$C$5="Katalog DSIC",'123450039'!$C$6=$A6),1,0)+IF(AND('123450115'!$C$5="Katalog DSIC",'123450115'!$C$6=$A6),1,0)+IF(AND('123450003'!$C$5="Katalog DSIC",'123450003'!$C$6=$A6),1,0)+IF(AND('123450029'!$C$5="Katalog DSIC",'123450029'!$C$6=$A6),1,0) -> #REF! | P6: =TEXTJOIN(", ",TRUE,IF(AND('123450063'!$C$5="Katalog DSIC",'123450063'!$C$6=$A6),"ARYA MUDA SIREGAR",""),IF(AND('1'!$C$5="Katalog DSIC",'1'!$C$6=$A6),"Desman Velius Halawa",""),IF(AND('123450104'!$C$5="Katalog DSIC",'123450104'!$C$6=$A6),"Fabio Banyu Cyto",""),IF(AND('123450039'!$C$5="Katalog DSIC",'123450039'!$C$6=$A6),"FEBY ANGELINA",""),IF(AND('123450115'!$C$5="Katalog DSIC",'123450115'!$C$6=$A6),"MUHAMMAD FADIL ALFAIZI",""),IF(AND('123450003'!$C$5="Katalog DSIC",'123450003'!$C$6=$A6),"Rahma Oktavia Albar",""),IF(AND('123450029'!$C$5="Katalog DSIC",'123450029'!$C$6=$A6),"Vania Claresta","")) -> #REF! | Q6: =IF(C6<>"Dibuka","Peta Jalan",IF(O6=0,"Tersedia",IF(O6=1,"Dipilih","Dipilih >1"))) -> #REF!
A7: DSIC26-04 | B7: 2026 | C7: Dibuka | D7: Ukuran Berkas Parquet yang Pas untuk Lakehouse Kecil | E7: Ukuran berkas berapa, dan pembagian data seperti apa, yang paling sesuai untuk kombinasi pemasukan data dan query analitik pada klaster kecil? | F7: Sistem analitik modern bekerja jauh lebih efisien jika hanya membaca bagian data yang diperlukan. Ukuran berkas yang terlalu kecil membuat sistem sibuk membuka-tutup berkas; yang terlalu besar membuat penyaringan menjadi kasar. | G7: Ukuran tetap 128 MB, 256 MB, dan 512 MB. | H7: Kebijakan ukuran berkas diturunkan dari beban kerja dan keterbatasan perangkat keras yang benar-benar ada. | I7: NYC TLC Trip Record Data dalam format Parquet, atau dataset tabular publik lain yang sudah disiapkan. | J7: Susun beberapa tata letak berkas. Jalankan pertanyaan analitik yang sama pada semuanya. Bandingkan waktu, jumlah byte yang dibaca, dan jumlah berkas yang tersentuh. | K7: Kamu bisa menunjukkan tata letak mana yang paling sesuai untuk jenis pertanyaan yang diuji, beserta konsekuensi penyimpanannya. | L7: Kamu suka pengelolaan data besar, penyimpanan, dan eksperimen yang sistematis. | M7: Skripsi; berpeluang menjadi naskah artikel bila hasilnya kuat. | N7: Klasik 8 · Terbaru 6, 7 | O7: =IF(AND('123450063'!$C$5="Katalog DSIC",'123450063'!$C$6=$A7),1,0)+IF(AND('1'!$C$5="Katalog DSIC",'1'!$C$6=$A7),1,0)+IF(AND('123450104'!$C$5="Katalog DSIC",'123450104'!$C$6=$A7),1,0)+IF(AND('123450039'!$C$5="Katalog DSIC",'123450039'!$C$6=$A7),1,0)+IF(AND('123450115'!$C$5="Katalog DSIC",'123450115'!$C$6=$A7),1,0)+IF(AND('123450003'!$C$5="Katalog DSIC",'123450003'!$C$6=$A7),1,0)+IF(AND('123450029'!$C$5="Katalog DSIC",'123450029'!$C$6=$A7),1,0) -> #REF! | P7: =TEXTJOIN(", ",TRUE,IF(AND('123450063'!$C$5="Katalog DSIC",'123450063'!$C$6=$A7),"ARYA MUDA SIREGAR",""),IF(AND('1'!$C$5="Katalog DSIC",'1'!$C$6=$A7),"Desman Velius Halawa",""),IF(AND('123450104'!$C$5="Katalog DSIC",'123450104'!$C$6=$A7),"Fabio Banyu Cyto",""),IF(AND('123450039'!$C$5="Katalog DSIC",'123450039'!$C$6=$A7),"FEBY ANGELINA",""),IF(AND('123450115'!$C$5="Katalog DSIC",'123450115'!$C$6=$A7),"MUHAMMAD FADIL ALFAIZI",""),IF(AND('123450003'!$C$5="Katalog DSIC",'123450003'!$C$6=$A7),"Rahma Oktavia Albar",""),IF(AND('123450029'!$C$5="Katalog DSIC",'123450029'!$C$6=$A7),"Vania Claresta","")) -> #REF! | Q7: =IF(C7<>"Dibuka","Peta Jalan",IF(O7=0,"Tersedia",IF(O7=1,"Dipilih","Dipilih >1"))) -> #REF!
A8: DSIC26-05 | B8: 2026 | C8: Dibuka | D8: Mengubah Cara Pembagian Data pada Tabel yang Terus Bertambah | E8: Kapan mengubah strategi partisi meningkatkan kemampuan sistem melewati berkas yang tidak relevan, tanpa membuat biaya perawatan tabel membengkak? | F8: Data yang terus bertambah membuat keputusan partisi awal cepat basi. Format tabel terbuka memungkinkan strategi partisi diubah tanpa menulis ulang seluruh tabel, tetapi setiap perubahan punya ongkos. | G8: Partisi statis yang ditentukan sekali di awal. | H8: Evaluasi partition evolution pada beban kerja bernuansa waktu dan lokasi, pada skala klaster kecil. | I8: NYC TLC Trip Record Data yang dimuat bertahap ke dalam tabel Apache Iceberg untuk meniru data yang terus tumbuh. | J8: Bangun tabel dengan partisi statis. Pada titik tertentu, ubah strategi partisinya. Jalankan query temporal dan spasial yang sama sebelum dan sesudah. Ukur jumlah berkas yang berhasil dilewati, waktu query, dan biaya penulisan ulang. | K8: Ada titik jelas kapan perubahan partisi terbayar dan kapan tidak, disertai angka biaya perawatannya. | L8: Kamu penasaran pada isi dapur lakehouse dan senang eksperimen bertahap. | M8: Skripsi + laporan teknis. | N8: Klasik 8 · Terbaru 6, 7, 8 | O8: =IF(AND('123450063'!$C$5="Katalog DSIC",'123450063'!$C$6=$A8),1,0)+IF(AND('1'!$C$5="Katalog DSIC",'1'!$C$6=$A8),1,0)+IF(AND('123450104'!$C$5="Katalog DSIC",'123450104'!$C$6=$A8),1,0)+IF(AND('123450039'!$C$5="Katalog DSIC",'123450039'!$C$6=$A8),1,0)+IF(AND('123450115'!$C$5="Katalog DSIC",'123450115'!$C$6=$A8),1,0)+IF(AND('123450003'!$C$5="Katalog DSIC",'123450003'!$C$6=$A8),1,0)+IF(AND('123450029'!$C$5="Katalog DSIC",'123450029'!$C$6=$A8),1,0) -> #REF! | P8: =TEXTJOIN(", ",TRUE,IF(AND('123450063'!$C$5="Katalog DSIC",'123450063'!$C$6=$A8),"ARYA MUDA SIREGAR",""),IF(AND('1'!$C$5="Katalog DSIC",'1'!$C$6=$A8),"Desman Velius Halawa",""),IF(AND('123450104'!$C$5="Katalog DSIC",'123450104'!$C$6=$A8),"Fabio Banyu Cyto",""),IF(AND('123450039'!$C$5="Katalog DSIC",'123450039'!$C$6=$A8),"FEBY ANGELINA",""),IF(AND('123450115'!$C$5="Katalog DSIC",'123450115'!$C$6=$A8),"MUHAMMAD FADIL ALFAIZI",""),IF(AND('123450003'!$C$5="Katalog DSIC",'123450003'!$C$6=$A8),"Rahma Oktavia Albar",""),IF(AND('123450029'!$C$5="Katalog DSIC",'123450029'!$C$6=$A8),"Vania Claresta","")) -> #REF! | Q8: =IF(C8<>"Dibuka","Peta Jalan",IF(O8=0,"Tersedia",IF(O8=1,"Dipilih","Dipilih >1"))) -> #REF!
A9: DSIC26-06 | B9: 2026 | C9: Dibuka | D9: Apa yang Terjadi Ketika Pipeline Gagal di Tengah Jalan? | E9: Bagaimana kombinasi pengulangan, titik simpan, dan operasi yang aman diulang memengaruhi kebenaran data ketika satu pekerja gagal di tengah proses pemasukan data? | F9: Dalam sistem terdistribusi, kegagalan bukan kejadian luar biasa melainkan kejadian biasa. Yang membedakan sistem yang baik adalah apakah ia bisa kembali ke keadaan benar setelah gagal, bukan apakah ia tidak pernah gagal. | G9: Pengulangan sederhana bergaya at-least-once. | H9: Yang diukur adalah kebenaran data setelah pemulihan, bukan sekadar berapa lama sistem kembali menyala. | I9: NYC TLC atau snapshot JADESTA yang dialirkan bertahap, dengan kegagalan yang sengaja dipicu pada titik-titik tertentu. | J9: Bangun pipeline sederhana. Suntikkan kegagalan pada beberapa titik berbeda. Untuk tiap strategi pemulihan, hitung jumlah data ganda, data hilang, dan waktu yang dibutuhkan untuk kembali konsisten. | K9: Ada tabel kebenaran data per strategi, dan kamu bisa menjelaskan strategi mana yang aman untuk jenis kegagalan yang mana. | L9: Kamu teliti dan terbiasa bertanya “bagaimana kalau ini gagal?” sebelum menulis kode. | M9: Skripsi tradisional. | N9: Klasik 7 · Terbaru 8 | O9: =IF(AND('123450063'!$C$5="Katalog DSIC",'123450063'!$C$6=$A9),1,0)+IF(AND('1'!$C$5="Katalog DSIC",'1'!$C$6=$A9),1,0)+IF(AND('123450104'!$C$5="Katalog DSIC",'123450104'!$C$6=$A9),1,0)+IF(AND('123450039'!$C$5="Katalog DSIC",'123450039'!$C$6=$A9),1,0)+IF(AND('123450115'!$C$5="Katalog DSIC",'123450115'!$C$6=$A9),1,0)+IF(AND('123450003'!$C$5="Katalog DSIC",'123450003'!$C$6=$A9),1,0)+IF(AND('123450029'!$C$5="Katalog DSIC",'123450029'!$C$6=$A9),1,0) -> #REF! | P9: =TEXTJOIN(", ",TRUE,IF(AND('123450063'!$C$5="Katalog DSIC",'123450063'!$C$6=$A9),"ARYA MUDA SIREGAR",""),IF(AND('1'!$C$5="Katalog DSIC",'1'!$C$6=$A9),"Desman Velius Halawa",""),IF(AND('123450104'!$C$5="Katalog DSIC",'123450104'!$C$6=$A9),"Fabio Banyu Cyto",""),IF(AND('123450039'!$C$5="Katalog DSIC",'123450039'!$C$6=$A9),"FEBY ANGELINA",""),IF(AND('123450115'!$C$5="Katalog DSIC",'123450115'!$C$6=$A9),"MUHAMMAD FADIL ALFAIZI",""),IF(AND('123450003'!$C$5="Katalog DSIC",'123450003'!$C$6=$A9),"Rahma Oktavia Albar",""),IF(AND('123450029'!$C$5="Katalog DSIC",'123450029'!$C$6=$A9),"Vania Claresta","")) -> #REF! | Q9: =IF(C9<>"Dibuka","Peta Jalan",IF(O9=0,"Tersedia",IF(O9=1,"Dipilih","Dipilih >1"))) -> #REF!
A10: DSIC26-07 | B10: 2026 | C10: Dibuka | D10: Mengapa Eksperimen yang Sama Bisa Memberi Hasil Berbeda? | E10: Seberapa besar perubahan versi basis data, runtime, atau container menggeser hasil benchmark yang seharusnya identik? | F10: Penelitian komputasi yang baik menyediakan cukup informasi agar orang lain dapat menjalankan ulang analisis dan memperoleh hasil sebanding. Kenyataannya, perbedaan kecil pada lingkungan sering menghasilkan selisih angka yang tidak kecil. | G10: Benchmark sekali jalan tanpa pencatatan terstruktur. | H10: Menamai dan mengukur pergeseran hasil antarversi sebagai fenomena tersendiri, bukan sekadar mengeluh soal hasil yang tidak stabil. | I10: NYC TLC atau benchmark yang sudah dipakai topik DSIC lain, sehingga fokusmu adalah cara mengulang eksperimen, bukan mencari data baru. | J10: Ulangi satu benchmark berkali-kali pada beberapa kombinasi versi dan lingkungan. Ukur sebaran hasilnya dan waktu yang dibutuhkan untuk menyiapkan tiap lingkungan. | K10: Ada angka yang menunjukkan besarnya variasi, dan kamu bisa menunjuk bagian mana yang menjadi sumber variasi terbesar. | L10: Kamu suka membuat proses rapi dan tertarik pada praktik penelitian yang jujur. | M10: Skripsi + laporan teknis. | N10: Klasik 9 · Terbaru 14, 15, 16 | O10: =IF(AND('123450063'!$C$5="Katalog DSIC",'123450063'!$C$6=$A10),1,0)+IF(AND('1'!$C$5="Katalog DSIC",'1'!$C$6=$A10),1,0)+IF(AND('123450104'!$C$5="Katalog DSIC",'123450104'!$C$6=$A10),1,0)+IF(AND('123450039'!$C$5="Katalog DSIC",'123450039'!$C$6=$A10),1,0)+IF(AND('123450115'!$C$5="Katalog DSIC",'123450115'!$C$6=$A10),1,0)+IF(AND('123450003'!$C$5="Katalog DSIC",'123450003'!$C$6=$A10),1,0)+IF(AND('123450029'!$C$5="Katalog DSIC",'123450029'!$C$6=$A10),1,0) -> #REF! | P10: =TEXTJOIN(", ",TRUE,IF(AND('123450063'!$C$5="Katalog DSIC",'123450063'!$C$6=$A10),"ARYA MUDA SIREGAR",""),IF(AND('1'!$C$5="Katalog DSIC",'1'!$C$6=$A10),"Desman Velius Halawa",""),IF(AND('123450104'!$C$5="Katalog DSIC",'123450104'!$C$6=$A10),"Fabio Banyu Cyto",""),IF(AND('123450039'!$C$5="Katalog DSIC",'123450039'!$C$6=$A10),"FEBY ANGELINA",""),IF(AND('123450115'!$C$5="Katalog DSIC",'123450115'!$C$6=$A10),"MUHAMMAD FADIL ALFAIZI",""),IF(AND('123450003'!$C$5="Katalog DSIC",'123450003'!$C$6=$A10),"Rahma Oktavia Albar",""),IF(AND('123450029'!$C$5="Katalog DSIC",'123450029'!$C$6=$A10),"Vania Claresta","")) -> #REF! | Q10: =IF(C10<>"Dibuka","Peta Jalan",IF(O10=0,"Tersedia",IF(O10=1,"Dipilih","Dipilih >1"))) -> #REF!
A11: DSIC26-08 | B11: 2026 | C11: Dibuka | D11: Sampai Titik Mana Menambah CPU dan RAM Masih Berguna? | E11: Pada titik mana penambahan CPU atau memori berhenti mempercepat PostgreSQL, Spark, dan Trino, dan pola penggunaan sumber daya seperti apa yang menandai munculnya hambatan? | F11: Dalam sistem yang terus menerima pekerjaan, hubungan antara jumlah pekerjaan yang menunggu, laju kedatangan, dan waktu tunggu membantu menjelaskan mengapa antrean muncul. Menambah sumber daya hanya menolong jika hambatannya memang di sana. | G11: Konfigurasi bawaan tanpa penyetelan. | H11: Peta empiris hubungan sumber daya dan performa untuk testbed terdistribusi berbiaya rendah. | I11: Catatan penggunaan sumber daya dari eksperimen standar, dengan subset Server Machine Dataset sebagai pembanding sekunder. | J11: Jalankan beban kerja yang sama pada beberapa konfigurasi sumber daya. Sengaja ciptakan hambatan pada CPU, memori, disk, dan jaringan secara bergantian. Catat pola penggunaan yang muncul pada tiap kasus. | K11: Ada kurva performa terhadap sumber daya beserta tanda khas untuk tiap jenis hambatan, lengkap dengan batas ketepatannya. | L11: Kamu tertarik pada server dan ingin benar-benar paham mengapa suatu proses melambat. | M11: Skripsi tradisional. | N11: Klasik 6, 16 · Terbaru 32, 33, 34 | O11: =IF(AND('123450063'!$C$5="Katalog DSIC",'123450063'!$C$6=$A11),1,0)+IF(AND('1'!$C$5="Katalog DSIC",'1'!$C$6=$A11),1,0)+IF(AND('123450104'!$C$5="Katalog DSIC",'123450104'!$C$6=$A11),1,0)+IF(AND('123450039'!$C$5="Katalog DSIC",'123450039'!$C$6=$A11),1,0)+IF(AND('123450115'!$C$5="Katalog DSIC",'123450115'!$C$6=$A11),1,0)+IF(AND('123450003'!$C$5="Katalog DSIC",'123450003'!$C$6=$A11),1,0)+IF(AND('123450029'!$C$5="Katalog DSIC",'123450029'!$C$6=$A11),1,0) -> #REF! | P11: =TEXTJOIN(", ",TRUE,IF(AND('123450063'!$C$5="Katalog DSIC",'123450063'!$C$6=$A11),"ARYA MUDA SIREGAR",""),IF(AND('1'!$C$5="Katalog DSIC",'1'!$C$6=$A11),"Desman Velius Halawa",""),IF(AND('123450104'!$C$5="Katalog DSIC",'123450104'!$C$6=$A11),"Fabio Banyu Cyto",""),IF(AND('123450039'!$C$5="Katalog DSIC",'123450039'!$C$6=$A11),"FEBY ANGELINA",""),IF(AND('123450115'!$C$5="Katalog DSIC",'123450115'!$C$6=$A11),"MUHAMMAD FADIL ALFAIZI",""),IF(AND('123450003'!$C$5="Katalog DSIC",'123450003'!$C$6=$A11),"Rahma Oktavia Albar",""),IF(AND('123450029'!$C$5="Katalog DSIC",'123450029'!$C$6=$A11),"Vania Claresta","")) -> #REF! | Q11: =IF(C11<>"Dibuka","Peta Jalan",IF(O11=0,"Tersedia",IF(O11=1,"Dipilih","Dipilih >1"))) -> #REF!
A12: DSIC26-09 | B12: 2026 | C12: Dibuka | D12: Kapan Satu Mesin Sudah Tidak Cukup? | E12: Pada ukuran data berapa pemrosesan dengan Spark mulai memberikan keuntungan waktu dibanding pemrosesan satu mesin dengan DuckDB? | F12: Membagi pekerjaan ke beberapa unit komputasi bisa mempercepat proses, tetapi selalu ada bagian yang tidak bisa dibagi dan selalu ada ongkos koordinasi. Karena itu pemrosesan terdistribusi tidak otomatis lebih cepat, terutama pada data yang belum cukup besar. | G12: DuckDB pada satu mesin. | H12: Titik impas yang diukur pada perangkat keras kelas laboratorium, bukan pada klaster awan berukuran besar. | I12: NYC TLC Trip Record Data pada beberapa ukuran yang sudah ditentukan. | J12: Jalankan tugas pengolahan data yang sama pada DuckDB dan Spark, pada beberapa ukuran dataset. Bandingkan waktu, penggunaan memori, dan penggunaan disk. | K12: Ada titik perbandingan yang jelas: pada ukuran tertentu satu mesin lebih efisien, dan pada ukuran lain pemrosesan terdistribusi mulai terbayar. | L12: Kamu penasaran dengan big data dan suka eksperimen performa yang objektif. | M12: Skripsi tradisional. | N12: Klasik 6, 7 · Terbaru 12 | O12: =IF(AND('123450063'!$C$5="Katalog DSIC",'123450063'!$C$6=$A12),1,0)+IF(AND('1'!$C$5="Katalog DSIC",'1'!$C$6=$A12),1,0)+IF(AND('123450104'!$C$5="Katalog DSIC",'123450104'!$C$6=$A12),1,0)+IF(AND('123450039'!$C$5="Katalog DSIC",'123450039'!$C$6=$A12),1,0)+IF(AND('123450115'!$C$5="Katalog DSIC",'123450115'!$C$6=$A12),1,0)+IF(AND('123450003'!$C$5="Katalog DSIC",'123450003'!$C$6=$A12),1,0)+IF(AND('123450029'!$C$5="Katalog DSIC",'123450029'!$C$6=$A12),1,0) -> #REF! | P12: =TEXTJOIN(", ",TRUE,IF(AND('123450063'!$C$5="Katalog DSIC",'123450063'!$C$6=$A12),"ARYA MUDA SIREGAR",""),IF(AND('1'!$C$5="Katalog DSIC",'1'!$C$6=$A12),"Desman Velius Halawa",""),IF(AND('123450104'!$C$5="Katalog DSIC",'123450104'!$C$6=$A12),"Fabio Banyu Cyto",""),IF(AND('123450039'!$C$5="Katalog DSIC",'123450039'!$C$6=$A12),"FEBY ANGELINA",""),IF(AND('123450115'!$C$5="Katalog DSIC",'123450115'!$C$6=$A12),"MUHAMMAD FADIL ALFAIZI",""),IF(AND('123450003'!$C$5="Katalog DSIC",'123450003'!$C$6=$A12),"Rahma Oktavia Albar",""),IF(AND('123450029'!$C$5="Katalog DSIC",'123450029'!$C$6=$A12),"Vania Claresta","")) -> #REF! | Q12: =IF(C12<>"Dibuka","Peta Jalan",IF(O12=0,"Tersedia",IF(O12=1,"Dipilih","Dipilih >1"))) -> #REF!
A13: DSIC27-01 | B13: 2027 | C13: Dibuka | D13: Pencarian Dokumen dengan Filter Metadata dan Asal-Usul | E13: Apakah menambahkan filter seperti kategori, bahasa, waktu, atau sumber meningkatkan ketepatan hasil pencarian dibanding hanya memakai kemiripan isi, dan berapa besar ongkosnya terhadap kelengkapan hasil? | F13: Dokumen dapat diwakili sebagai titik dalam ruang matematis, dan hasil pencarian dinilai dengan ukuran seperti recall dan kualitas peringkat. Menambahkan syarat metadata terdengar sepele, tetapi mengubah cara indeks vektor harus ditelusuri. | G13: Pencarian berbasis kemiripan semantik saja. | H13: Retrieval yang mengoptimalkan relevansi sekaligus kejelasan asal-usul data. | I13: MIRACL bagian Bahasa Indonesia, dataset publik untuk penelitian pencarian informasi multibahasa. | J13: Jalankan pencarian dasar. Tambahkan satu atau dua filter metadata yang relevan. Bandingkan ketepatan, kelengkapan, dan waktu pencarian pada beberapa tingkat selektivitas filter. | K13: Ada hasil yang menunjukkan apakah filter metadata menolong, tidak menolong, atau hanya menolong pada jenis pertanyaan tertentu. | L13: Kamu tertarik pada mesin pencari, chatbot, atau RAG, tetapi ingin fokus pada sisi data dan pencarian. | M13: Skripsi; berpeluang menjadi naskah artikel bila hasilnya kuat. | N13: Klasik 10, 11 · Terbaru 21, 22, 23, 24, 25 | O13: =IF(AND('123450063'!$C$5="Katalog DSIC",'123450063'!$C$6=$A13),1,0)+IF(AND('1'!$C$5="Katalog DSIC",'1'!$C$6=$A13),1,0)+IF(AND('123450104'!$C$5="Katalog DSIC",'123450104'!$C$6=$A13),1,0)+IF(AND('123450039'!$C$5="Katalog DSIC",'123450039'!$C$6=$A13),1,0)+IF(AND('123450115'!$C$5="Katalog DSIC",'123450115'!$C$6=$A13),1,0)+IF(AND('123450003'!$C$5="Katalog DSIC",'123450003'!$C$6=$A13),1,0)+IF(AND('123450029'!$C$5="Katalog DSIC",'123450029'!$C$6=$A13),1,0) -> #REF! | P13: =TEXTJOIN(", ",TRUE,IF(AND('123450063'!$C$5="Katalog DSIC",'123450063'!$C$6=$A13),"ARYA MUDA SIREGAR",""),IF(AND('1'!$C$5="Katalog DSIC",'1'!$C$6=$A13),"Desman Velius Halawa",""),IF(AND('123450104'!$C$5="Katalog DSIC",'123450104'!$C$6=$A13),"Fabio Banyu Cyto",""),IF(AND('123450039'!$C$5="Katalog DSIC",'123450039'!$C$6=$A13),"FEBY ANGELINA",""),IF(AND('123450115'!$C$5="Katalog DSIC",'123450115'!$C$6=$A13),"MUHAMMAD FADIL ALFAIZI",""),IF(AND('123450003'!$C$5="Katalog DSIC",'123450003'!$C$6=$A13),"Rahma Oktavia Albar",""),IF(AND('123450029'!$C$5="Katalog DSIC",'123450029'!$C$6=$A13),"Vania Claresta","")) -> #REF! | Q13: =IF(C13<>"Dibuka","Peta Jalan",IF(O13=0,"Tersedia",IF(O13=1,"Dipilih","Dipilih >1"))) -> #REF!
A14: DSIC27-02 | B14: 2027 | C14: Dibuka | D14: Kapan Embedding Perlu Dihitung Ulang? | E14: Setelah data sumber berubah, perubahan seperti apa yang benar-benar mengharuskan embedding dihitung ulang? | F14: Embedding adalah rangkuman makna sebuah dokumen dalam bentuk angka. Ketika dokumen aslinya berubah, rangkuman itu bisa menjadi usang. Menghitung ulang semuanya selalu aman, tetapi mahal. | G14: Menghitung ulang seluruh embedding setiap kali ada perubahan. | H14: Kebijakan pembaruan selektif berdasarkan besar dan jenis perubahan, bukan berdasarkan jadwal. | I14: MIRACL Bahasa Indonesia atau koleksi dokumen publik, dengan beberapa versi perubahan yang disimulasikan: koreksi kecil, penulisan ulang, dan dokumen baru. | J14: Buat beberapa kelas perubahan dokumen. Bandingkan kebijakan pembaruan selektif dengan pembaruan menyeluruh, dari sisi kualitas hasil pencarian dan biaya komputasi. | K14: Ada aturan sederhana yang bisa kamu pertanggungjawabkan tentang perubahan seperti apa yang layak memicu perhitungan ulang. | L14: Kamu suka memikirkan efisiensi dan tidak nyaman melihat komputasi yang terbuang. | M14: Skripsi + draf artikel bila hasilnya layak. | N14: Klasik 10 · Terbaru 17, 22 | O14: =IF(AND('123450063'!$C$5="Katalog DSIC",'123450063'!$C$6=$A14),1,0)+IF(AND('1'!$C$5="Katalog DSIC",'1'!$C$6=$A14),1,0)+IF(AND('123450104'!$C$5="Katalog DSIC",'123450104'!$C$6=$A14),1,0)+IF(AND('123450039'!$C$5="Katalog DSIC",'123450039'!$C$6=$A14),1,0)+IF(AND('123450115'!$C$5="Katalog DSIC",'123450115'!$C$6=$A14),1,0)+IF(AND('123450003'!$C$5="Katalog DSIC",'123450003'!$C$6=$A14),1,0)+IF(AND('123450029'!$C$5="Katalog DSIC",'123450029'!$C$6=$A14),1,0) -> #REF! | P14: =TEXTJOIN(", ",TRUE,IF(AND('123450063'!$C$5="Katalog DSIC",'123450063'!$C$6=$A14),"ARYA MUDA SIREGAR",""),IF(AND('1'!$C$5="Katalog DSIC",'1'!$C$6=$A14),"Desman Velius Halawa",""),IF(AND('123450104'!$C$5="Katalog DSIC",'123450104'!$C$6=$A14),"Fabio Banyu Cyto",""),IF(AND('123450039'!$C$5="Katalog DSIC",'123450039'!$C$6=$A14),"FEBY ANGELINA",""),IF(AND('123450115'!$C$5="Katalog DSIC",'123450115'!$C$6=$A14),"MUHAMMAD FADIL ALFAIZI",""),IF(AND('123450003'!$C$5="Katalog DSIC",'123450003'!$C$6=$A14),"Rahma Oktavia Albar",""),IF(AND('123450029'!$C$5="Katalog DSIC",'123450029'!$C$6=$A14),"Vania Claresta","")) -> #REF! | Q14: =IF(C14<>"Dibuka","Peta Jalan",IF(O14=0,"Tersedia",IF(O14=1,"Dipilih","Dipilih >1"))) -> #REF!
A15: DSIC27-03 | B15: 2027 | C15: Dibuka | D15: Menggabungkan Skor Kata Kunci, Kemiripan Makna, dan Keyakinan Sumber | E15: Apakah menggabungkan skor pencocokan kata, kemiripan vektor, dan tingkat keyakinan sumber menghasilkan urutan hasil yang lebih baik daripada memakai salah satunya saja? | F15: Pencocokan kata kunci kuat pada istilah spesifik; pencarian vektor kuat pada makna. Menggabungkan keduanya sudah umum. Yang belum umum adalah memasukkan seberapa dapat dipercaya sumber sebuah dokumen ke dalam perhitungan peringkat. | G15: BM25 saja, lalu pencarian vektor saja. | H15: Peringkat yang mempertimbangkan relevansi makna sekaligus kekuatan bukti. | I15: MIRACL Bahasa Indonesia. | J15: Bangun tiga sistem: leksikal, vektor, dan gabungan. Tambahkan komponen keyakinan sumber. Ukur kualitas peringkat pada pertanyaan yang sama dan lihat jenis pertanyaan mana yang paling terbantu. | K15: Ada perbandingan kualitas peringkat antarpendekatan dan penjelasan tentang bobot yang masuk akal. | L15: Kamu suka mengutak-atik peringkat hasil pencarian dan senang membaca metrik evaluasi. | M15: Skripsi; berpeluang menjadi naskah artikel bila hasilnya kuat. | N15: Klasik 10, 11 · Terbaru 17, 21 | O15: =IF(AND('123450063'!$C$5="Katalog DSIC",'123450063'!$C$6=$A15),1,0)+IF(AND('1'!$C$5="Katalog DSIC",'1'!$C$6=$A15),1,0)+IF(AND('123450104'!$C$5="Katalog DSIC",'123450104'!$C$6=$A15),1,0)+IF(AND('123450039'!$C$5="Katalog DSIC",'123450039'!$C$6=$A15),1,0)+IF(AND('123450115'!$C$5="Katalog DSIC",'123450115'!$C$6=$A15),1,0)+IF(AND('123450003'!$C$5="Katalog DSIC",'123450003'!$C$6=$A15),1,0)+IF(AND('123450029'!$C$5="Katalog DSIC",'123450029'!$C$6=$A15),1,0) -> #REF! | P15: =TEXTJOIN(", ",TRUE,IF(AND('123450063'!$C$5="Katalog DSIC",'123450063'!$C$6=$A15),"ARYA MUDA SIREGAR",""),IF(AND('1'!$C$5="Katalog DSIC",'1'!$C$6=$A15),"Desman Velius Halawa",""),IF(AND('123450104'!$C$5="Katalog DSIC",'123450104'!$C$6=$A15),"Fabio Banyu Cyto",""),IF(AND('123450039'!$C$5="Katalog DSIC",'123450039'!$C$6=$A15),"FEBY ANGELINA",""),IF(AND('123450115'!$C$5="Katalog DSIC",'123450115'!$C$6=$A15),"MUHAMMAD FADIL ALFAIZI",""),IF(AND('123450003'!$C$5="Katalog DSIC",'123450003'!$C$6=$A15),"Rahma Oktavia Albar",""),IF(AND('123450029'!$C$5="Katalog DSIC",'123450029'!$C$6=$A15),"Vania Claresta","")) -> #REF! | Q15: =IF(C15<>"Dibuka","Peta Jalan",IF(O15=0,"Tersedia",IF(O15=1,"Dipilih","Dipilih >1"))) -> #REF!
... A45: DSIC30-08 | B45: 2030 | C45: Peta jalan | D45: Mengatur Jumlah Pekerja dari Telemetri yang Sedang Berjalan | E45: Bisakah telemetri saat proses berjalan dipakai untuk menentukan jumlah pekerja dan tingkat konkurensi untuk beban kerja multimodal? | F45: Menetapkan jumlah pekerja di awal berarti menebak. Umpan balik dari sistem yang sedang berjalan memungkinkan penyesuaian di tengah jalan, dengan risiko sistem menjadi goyah bila terlalu cepat bereaksi. | G45: Tingkat konkurensi tetap. | H45: Pendekatan kendali berumpan balik untuk pipeline data dan AI. | I45: Beban kerja multimodal pada klaster kecil. | J45: Bangun pengendali sederhana. Bandingkan dengan konfigurasi tetap dari sisi waktu penyelesaian, kestabilan, dan pemakaian sumber daya. | K45: Ada bukti apakah pengendalian berumpan balik menolong, dan pada titik mana ia mulai membuat sistem tidak stabil. | L45: Kamu tertarik pada sistem kendali dan senang melihat sistem menyesuaikan dirinya. | M45: Skripsi + laporan teknis. | N45: Klasik 6, 16 · Terbaru 36, 37, 39 | O45: =IF(AND('123450063'!$C$5="Katalog DSIC",'123450063'!$C$6=$A45),1,0)+IF(AND('1'!$C$5="Katalog DSIC",'1'!$C$6=$A45),1,0)+IF(AND('123450104'!$C$5="Katalog DSIC",'123450104'!$C$6=$A45),1,0)+IF(AND('123450039'!$C$5="Katalog DSIC",'123450039'!$C$6=$A45),1,0)+IF(AND('123450115'!$C$5="Katalog DSIC",'123450115'!$C$6=$A45),1,0)+IF(AND('123450003'!$C$5="Katalog DSIC",'123450003'!$C$6=$A45),1,0)+IF(AND('123450029'!$C$5="Katalog DSIC",'123450029'!$C$6=$A45),1,0) -> #REF! | P45: =TEXTJOIN(", ",TRUE,IF(AND('123450063'!$C$5="Katalog DSIC",'123450063'!$C$6=$A45),"ARYA MUDA SIREGAR",""),IF(AND('1'!$C$5="Katalog DSIC",'1'!$C$6=$A45),"Desman Velius Halawa",""),IF(AND('123450104'!$C$5="Katalog DSIC",'123450104'!$C$6=$A45),"Fabio Banyu Cyto",""),IF(AND('123450039'!$C$5="Katalog DSIC",'123450039'!$C$6=$A45),"FEBY ANGELINA",""),IF(AND('123450115'!$C$5="Katalog DSIC",'123450115'!$C$6=$A45),"MUHAMMAD FADIL ALFAIZI",""),IF(AND('123450003'!$C$5="Katalog DSIC",'123450003'!$C$6=$A45),"Rahma Oktavia Albar",""),IF(AND('123450029'!$C$5="Katalog DSIC",'123450029'!$C$6=$A45),"Vania Claresta","")) -> #REF! | Q45: =IF(C45<>"Dibuka","Peta Jalan",IF(O45=0,"Tersedia",IF(O45=1,"Dipilih","Dipilih >1"))) -> Peta Jalan
A46: DSIC-SDG1 | B46: 2026 | C46: Dibuka | D46: Memilih Konfigurasi Data Product Berdasarkan Karakteristik Workload | E46: Dapatkah karakteristik data dan workload digunakan untuk memprediksi konfigurasi data product yang lebih efisien dibandingkan memakai satu konfigurasi tetap untuk seluruh domain? Sub-pertanyaan: karakteristik workload apa yang paling berpengaruh terhadap pilihan konfigurasi? | F46: Tidak semua data mempunyai karakter yang sama. Ada data dengan banyak tahun, banyak indikator, cardinality tinggi, ukuran besar, pembaruan berkala, atau pola query tertentu. Konfigurasi yang baik untuk satu workload belum tentu baik untuk workload lain. Penelitian ini memandang pemilihan konfigurasi sebagai masalah workload-to-configuration mapping: profil workload menjadi masukan, sedangkan konfigurasi sistem menjadi keputusan. | G46: Fixed configuration, yaitu seluruh workload menggunakan konfigurasi yang sama. Tambahan: simple rule/heuristic berbasis ukuran data sebagai baseline kedua. | H46: Menguji apakah profil workload official statistics dapat digunakan untuk memilih konfigurasi secara otomatis, lalu mengujinya pada domain SDG yang tidak digunakan saat membentuk aturan/model pemilihan. Kebaruan bukan algoritma ML baru, tetapi validitas workload-aware configuration selection lintas domain heterogen. | I46: Data indikator resmi SDG 4, 6, 7, 8, dan 15dari BPS. SDG 4 dan 6 dapat dipakai untuk profiling/development; SDG 7, 8, dan 15 untuk held-out evaluation. | J46: Bulan 1: definisikan workload features dan candidate configurations; bangun benchmark harness. Bulan 2:jalankan profiling seluruh konfigurasi pada development workloads dan bentuk rule/model selector. Bulan 3:bekukan selector lalu uji pada held-out workloads. Bulan 4:analisis error, feature importance, trade-off, statistik, dan penulisan artikel. | K46: Ada tabel workload → konfigurasi terbaik, baseline fixed, selector yang dibekukan sebelum held-out test, hasil pada minimal tiga domain held-out, pengukuran runtime/resource/query cost, serta analisis kapan selector berhasil dan gagal. | L46: Kamu tertarik machine learning tetapi ingin bekerja pada masalah data systems, suka profiling, eksperimen, Python, dan analisis hubungan karakteristik workload dengan performa sistem. | M46: Skripsi + artikel mahasiswa.Berkontribusi ke artikel integrasi KK-CIV sebagai komponen workload-to-configuration selector.
A47: DSIC-SDG2 | B47: 2026 | C47: Dibuka | D47: Strategi Penyimpanan Adaptif untuk Workload Analitik Data SDGs | E47: Kapan strategi partitioning dan ukuran file yang berbeda memberikan performa terbaik untuk workload analitik official statistics, dan dapatkah karakteristik workload digunakan untuk memilih strategi tersebut secara adaptif? | F47: Data lakehouse menyimpan data dalam banyak file dan partisi. Partitioning dapat mempercepat query karena sistem tidak perlu membaca seluruh data, tetapi terlalu banyak partisi atau file kecil juga menambah overhead. Karena itu tidak ada satu desain fisik yang selalu terbaik. Penelitian mempelajari hubungan query pattern – partitioning – file layout – cost pada Apache Iceberg. | G47: Unpartitioned Iceberg table dan satu partitioning statisyang diterapkan ke seluruh workload, misalnya berdasarkan tahun. | H47: Pemilihan physical design Iceberg berdasarkan workload pada data official statistics yang memiliki perbedaan grain, temporal depth, cardinality, dan pola filter. Fokus bukan menciptakan teknik partitioning baru, tetapi menentukan kapan konfigurasi fisik tertentu layak dipilihdan apakah aturan tersebut dapat ditransfer ke workload lain. | I47: SDG 4, 6, 7, dan 8sebagai workload tabular/temporal utama. SDG 15 hanya atribut non-geometri bila dibutuhkan untuk kontrol. Seluruh eksperimen memakai snapshot data dan query workload yang sama. | J47: Bulan 1: bentuk workload query representatif dan baseline Iceberg. Bulan 2:eksperimen unpartitioned, partition by year, region, indicator, dan kombinasi terbatas; uji ukuran/file layout yang dibekukan. Bulan 3:bentuk workload-aware selection rule dan uji pada query/domain held-out. Bulan 4: analisis query plan, bytes/files scanned, latency, storage overhead, failure cases, dan artikel. | K47: Untuk setiap workload tersedia latency, files/bytes scanned, storage overhead dan query plan; terdapat baseline statis; tersedia aturan kapan physical design tertentu menguntungkan; dan aturan tersebut diuji pada workload yang tidak dipakai saat merancangnya. | L47: Kamu senang SQL, Spark/Trino, query plan, Iceberg, dan eksperimen performa serta ingin penelitian Data Systems yang hasilnya sangat terukur. | M47: Skripsi + artikel mahasiswa.Hasil dapat menjadi modul adaptive physical design pada platform KK-CIV.
A48: DSIC-SDG3 | B48: 2026 | C48: Dibuka | D48: Pemilihan Materialisasi Adaptif untuk Query Analitik SDGs yang Berulang | E48: Dapatkah pola query digunakan untuk menentukan agregat atau hasil antara yang perlu dimaterialisasi sehingga query berulang menjadi lebih cepat tanpa menambah biaya penyimpanan dan pemeliharaan secara berlebihan? | F48: Query analitik sering menghitung agregasi yang sama berulang kali, misalnya indikator per provinsi, tahun, atau kelompok domain. Menyimpan hasil yang sudah dihitung dapat mempercepat query berikutnya, tetapi materialisasi membutuhkan ruang dan harus diperbarui ketika data berubah. Masalahnya adalah memilih apa yang layak disimpan dan apa yang lebih baik dihitung ulang. | G48: No materialization, yaitu seluruh query selalu dihitung dari Gold table. Baseline tambahan: materialize-all, yaitu semua kandidat agregasi disimpan tanpa mempertimbangkan pola penggunaan. | H48: Menggunakan profil frekuensi, biaya, dan pola query untuk memilih materialization candidate pada workload official statistics. Evaluasi menekankan trade-off antara query latency, storage cost, dan refresh cost, bukan hanya mengejar query tercepat. | I48: Gold data products SDG 4, 6, 7, dan 8. Dibuat workload query terkontrol yang mencakup filter waktu, wilayah, indikator, aggregation, dan kombinasi yang berulang dengan frekuensi berbeda. | J48: Bulan 1: susun query workload dan ukur no-materialization baseline. Bulan 2: definisikan kandidat agregat/materialized results dan ukur benefit serta maintenance cost. Bulan 3:bangun policy pemilihan berdasarkan workload dan uji pada query trace yang berbeda/held-out. Bulan 4:evaluasi Pareto query latency–storage–refresh cost, failure analysis, dan penulisan. | K48: Tersedia no-materialization dan materialize-all baseline; query trace dibekukan; policy memilih subset materialization; tersedia latency, storage footprint dan refresh cost; serta dapat dijelaskan kapan materialisasi membantu dan kapan biaya pemeliharaannya tidak sebanding. | L48: Kamu suka SQL dan analitik performa, tertarik dengan caching/materialized views dan ingin penelitian database tanpa harus membuat model AI yang berat. | M48: Skripsi + artikel mahasiswa.Hasil menjadi komponen adaptive materializationuntuk artikel sistem KK-CIV.
A49: DSIC-SDG4 | B49: 2026 | C49: Dibuka | D49: Memilih Konfigurasi Penyimpanan dan Query untuk Workload Spasial SDGs | E49: Bagaimana karakteristik workload spasial memengaruhi pilihan konfigurasi penyimpanan dan eksekusi query, dan konfigurasi mana yang memberi trade-off terbaik untuk analitik spasial official statistics? | F49: Data spasial berbeda dari tabel biasa karena setiap record dapat memiliki geometri dan operasi seperti spatial join, intersection, containment, atau pencarian tetangga. Representasi, partitioning, spatial indexing, dan strategi join dapat menghasilkan biaya yang sangat berbeda. Penelitian ini mencari hubungan antara karakteristik spatial workload dan konfigurasi eksekusi yang sesuai. | G49: Konfigurasi spasial statis, yaitu satu representasi/partitioning dan satu strategi query digunakan untuk semua workload. Baseline sederhana menggunakan spatial join tanpa optimasi/adaptive configuration. | H49: Evaluasi workload-aware spatial configurationpada official-statistics data product yang menggabungkan indikator BPS dengan reference geometry. Kontribusinya adalah menentukan kondisi kapan konfigurasi spasial tertentu lebih menguntungkan serta menguji apakah keputusan dapat dibuat dari profil workload, bukan membuat algoritma spatial join baru. | I49: SDG 15 sebagai dataset utama: indikator BPS tingkat provinsi + geometri provinsi sebagai reference/master data. Untuk variasi workload digunakan point/range/filter/spatial join/neighborhood queries dan ukuran data yang dikontrol. | J49: Bulan 1: siapkan Gold SDG 15, geometry master dan query workload. Bulan 2:benchmark beberapa konfigurasi representasi/partitioning/spatial strategy yang sudah tersedia. Bulan 3: bentuk aturan pemilihan berdasarkan workload dan lakukan held-out query validation. Bulan 4:analisis runtime, data scanned, memory, spatial correctness, overhead, failure cases, dan artikel. | K49: Minimal satu baseline dan beberapa candidate configurations telah dibandingkan pada query spasial yang sama; correctness hasil divalidasi; tersedia latency/resource cost; ada workload-aware selection rule; dan dapat dijelaskan konfigurasi mana cocok untuk tipe spatial workload tertentu. | L49: Kamu tertarik data geospasial, GeoPandas/Sedona/PostGIS, query processing, dan ingin berada di antara Data Systems dan spatial computing. | M49: Skripsi + artikel mahasiswa.Hasil menjadi spatial workload configuration module dan external/stress component untuk artikel integrasi KK-CIV.

Sheet KATALOG_REFERENSI
A1: KATALOG REFERENSI — BUKU / ARTIKEL / PAPER
A2: Daftar referensi sudah dipetakan dari katalog topik. Isi kolom Link ketika URL/DOI/tautan buku sudah tersedia.
A3: ID | B3: Kategori | C3: Referensi | D3: Link | E3: Topik Terkait | F3: Status Baca | G3: Catatan
A4: K1 | B4: Klasik | C4: Codd, E. F. (1970). A Relational Model of Data for Large Shared Data Banks. Communications of the ACM, 13(6), 377–387. | E4: DSIC27-09 | F4: Belum
A5: K2 | B5: Klasik | C5: Bayer, R., & McCreight, E. (1972). Organization and Maintenance of Large Ordered Indexes. Acta Informatica, 1, 173–189. | E5: DSIC26-01, DSIC28-07, DSIC29-02 | F5: Belum
A6: K3 | B6: Klasik | C6: Selinger, P. G., Astrahan, M. M., Chamberlin, D. D., Lorie, R. A., & Price, T. G. (1979). Access Path Selection in a Relational Database Management System. Proceedings of ACM SIGMOD. | E6: DSIC26-01, DSIC29-02, DSIC29-03 | F6: Belum
A7: K4 | B7: Klasik | C7: Buneman, P., Khanna, S., & Tan, W.-C. (2001). Why and Where: A Characterization of Data Provenance. International Conference on Database Theory (ICDT). | E7: DSIC26-02, DSIC28-05, DSIC30-07 | F7: Belum
A8: K5 | B8: Klasik | C8: Wang, R. Y., & Strong, D. M. (1996). Beyond Accuracy: What Data Quality Means to Data Consumers. Journal of Management Information Systems, 12(4), 5–33. | E8: DSIC26-03, DSIC29-05, DSIC29-06 | F8: Belum
A9: K6 | B9: Klasik | C9: Amdahl, G. M. (1967). Validity of the Single Processor Approach to Achieving Large Scale Computing Capabilities. AFIPS Conference Proceedings. | E9: DSIC26-08, DSIC26-09, DSIC28-03, DSIC29-04, DSIC29-07, DSIC30-04, DSIC30-08 | F9: Belum
A10: K7 | B10: Klasik | C10: Dean, J., & Ghemawat, S. (2008). MapReduce: Simplified Data Processing on Large Clusters. Communications of the ACM, 51(1), 107–113. | E10: DSIC26-06, DSIC26-09, DSIC28-08, DSIC29-04 | F10: Belum
A11: K8 | B11: Klasik | C11: Abadi, D., Boncz, P., Harizopoulos, S., Idreos, S., & Madden, S. (2013). The Design and Implementation of Modern Column-Oriented Database Systems. Foundations and Trends in Databases, 5(3), 197–280. | E11: DSIC26-04, DSIC26-05, DSIC28-01, DSIC28-04, DSIC28-07, DSIC29-01, DSIC29-08, DSIC30-06 | F11: Belum
A12: K9 | B12: Klasik | C12: Peng, R. D. (2011). Reproducible Research in Computational Science. Science, 334(6060), 1226–1227. | E12: DSIC26-07 | F12: Belum
A13: K10 | B13: Klasik | C13: Salton, G., Wong, A., & Yang, C. S. (1975). A Vector Space Model for Automatic Indexing. Communications of the ACM, 18(11), 613–620. | E13: DSIC27-01, DSIC27-02, DSIC27-03, DSIC28-02, DSIC28-05, DSIC30-01, DSIC30-02, DSIC30-03, DSIC30-05 | F13: Belum
A14: K11 | B14: Klasik | C14: Manning, C. D., Raghavan, P., & Schütze, H. (2008). Introduction to Information Retrieval. Cambridge University Press. | E14: DSIC27-01, DSIC27-03, DSIC28-02, DSIC30-01 | F14: Belum
A15: K12 | B15: Klasik | C15: Lewis, P., Perez, E., Piktus, A., et al. (2020). Retrieval-Augmented Generation for Knowledge-Intensive NLP Tasks. NeurIPS. | E15: DSIC27-04, DSIC27-05, DSIC30-07 | F15: Belum
... A19: K16 | B19: Klasik | C19: Little, J. D. C. (1961). A Proof for the Queuing Formula: L = λW. Operations Research, 9(3), 383–387. | E19: DSIC26-08, DSIC29-05, DSIC29-07, DSIC30-08 | F19: Belum
A20: K17 | B20: Klasik | C20: Piczak, K. J. (2015). ESC: Dataset for Environmental Sound Classification. Proceedings of the ACM International Conference on Multimedia. | F20: Belum
A21: T1 | B21: Terbaru | C21: Kossmann, J., Kastius, A., & Schlosser, R. (2022). SWIRL: Selection of Workload-aware Indexes using Reinforcement Learning. EDBT 2022. | E21: DSIC26-01, DSIC29-02 | F21: Belum
A22: T2 | B22: Terbaru | C22: Sharma, V., & Dyreson, C. (2022). Indexer++: Workload-aware Online Index Tuning with Transformers and Reinforcement Learning. ACM SAC 2022. | F22: Belum
A23: T3 | B23: Terbaru | C23: Zhou, W., Lin, C., Zhou, X., & Li, G. (2024). Breaking It Down: An In-Depth Study of Index Advisors. PVLDB, 17(10), 2405–2418. | E23: DSIC26-01, DSIC29-02 | F23: Belum
A24: T4 | B24: Terbaru | C24: Wu, Y., Zhou, X., Zhang, Y., & Li, G. (2024). Automatic Index Tuning: A Survey. IEEE Transactions on Knowledge and Data Engineering, 36(12), 7657–7676. | E24: DSIC26-01, DSIC29-02 | F24: Belum
A25: T5 | B25: Terbaru | C25: Siddiqui, T., & Wu, W. (2024). ML-Powered Index Tuning: An Overview of Recent Progress and Open Challenges. ACM SIGMOD Record, 52(4), 19–30. | E25: DSIC26-01, DSIC29-02 | F25: Belum
A26: T6 | B26: Terbaru | C26: Jain, P., et al. (2023). Analyzing and Comparing Lakehouse Storage Systems (LHBench). CIDR 2023. | E26: DSIC26-02, DSIC26-04, DSIC26-05, DSIC28-01, DSIC29-08 | F26: Belum
A27: T7 | B27: Terbaru | C27: AutoComp: Automated Data Compaction for Log-Structured Tables in Data Lakes. (2025). arXiv:2504.04186. | E27: DSIC26-02, DSIC26-04, DSIC26-05, DSIC28-01, DSIC28-04, DSIC29-08 | F27: Belum
A28: T8 | B28: Terbaru | C28: LakeVilla: A Modular and Non-Invasive Toolbox for Lakehouse Transactions. (2025). arXiv:2504.20768. | E28: DSIC26-02, DSIC26-05, DSIC26-06, DSIC28-04, DSIC28-08 | F28: Belum
A29: T9 | B29: Terbaru | C29: Zha, D., Bhat, Z. P., Lai, K.-H., Yang, F., Jiang, Z., Zhong, S., & Hu, X. (2025). Data-centric Artificial Intelligence: A Survey. ACM Computing Surveys. | E29: DSIC26-03, DSIC29-06 | F29: Belum
A30: T10 | B30: Terbaru | C30: A Survey on Data Quality Dimensions and Tools for Machine Learning. (2024). arXiv:2406.19614. | E30: DSIC26-03, DSIC29-05, DSIC29-06 | F30: Belum
A31: T11 | B31: Terbaru | C31: Whang, S. E., Roh, Y., Song, H., & Lee, J.-G. (2023). Data Collection and Quality Challenges in Deep Learning: A Data-Centric AI Perspective. The VLDB Journal, 32(4), 791–813. | E31: DSIC26-03, DSIC29-05, DSIC29-06 | F31: Belum
A32: T12 | B32: Terbaru | C32: van Renen, A., & Leis, V. (2023). Cloud Analytics Benchmark. PVLDB, 16(6), 1413–1425. | E32: DSIC26-09, DSIC29-04 | F32: Belum
A33: T13 | B33: Terbaru | C33: Zhou, X., Chai, C., Li, G., & Sun, J. (2022). Database Meets Artificial Intelligence: A Survey. IEEE Transactions on Knowledge and Data Engineering, 34(3). | F33: Belum
A34: T14 | B34: Terbaru | C34: Semmelrock, H., et al. (2025). Reproducibility in Machine-Learning-Based Research: Overview, Barriers, and Drivers. AI Magazine. | E34: DSIC26-07 | F34: Belum
A35: T15 | B35: Terbaru | C35: Reproducibility of Machine Learning: Terminology, Recommendations and Open Issues. (2023). arXiv:2302.12691. | E35: DSIC26-07 | F35: Belum
A36: T16 | B36: Terbaru | C36: Containers for Computational Reproducibility. (2023). Nature Reviews Methods Primers, 3, 50. | E36: DSIC26-07 | F36: Belum
A37: T17 | B37: Terbaru | C37: Gao, Y., Xiong, Y., Gao, X., Jia, K., Pan, J., Bi, Y., Dai, Y., Sun, J., Wang, M., & Wang, H. (2024). Retrieval-Augmented Generation for Large Language Models: A Survey. arXiv:2312.10997. | E37: DSIC27-02, DSIC27-03, DSIC27-04, DSIC27-05, DSIC30-01, DSIC30-05, DSIC30-07 | F37: Belum
A38: T18 | B38: Terbaru | C38: Qu, R., Tu, R., & Bao, F. S. (2025). Is Semantic Chunking Worth the Computational Cost? Findings of NAACL 2025. | E38: DSIC27-04 | F38: Belum
A39: T19 | B39: Terbaru | C39: Merola, C., & Singh, J. (2025). Reconstructing Context: Evaluating Advanced Chunking Strategies for Retrieval-Augmented Generation. arXiv:2504.19754. | E39: DSIC27-04, DSIC27-05 | F39: Belum
A40: T20 | B40: Terbaru | C40: Es, S., James, J., Espinosa-Anke, L., & Schockaert, S. (2024). RAGAS: Automated Evaluation of Retrieval Augmented Generation. EACL 2024. | E40: DSIC27-04, DSIC27-05, DSIC30-07 | F40: Belum
A41: T21 | B41: Terbaru | C41: Zhang, X., Thakur, N., Ogundepo, O., Kamalloo, E., et al. (2023). MIRACL: A Multilingual Retrieval Dataset Covering 18 Diverse Languages. Transactions of the ACL, 11. | E41: DSIC27-01, DSIC27-03, DSIC30-01 | F41: Belum
A42: T22 | B42: Terbaru | C42: Pan, J. J., Wang, J., & Li, G. (2024). Survey of Vector Database Management Systems. The VLDB Journal, 33(5), 1591–1615. | E42: DSIC27-01, DSIC27-02, DSIC28-02, DSIC28-05, DSIC28-06, DSIC28-07, DSIC30-02, DSIC30-03, DSIC30-05, DSIC30-06 | F42: Belum
A43: T23 | B43: Terbaru | C43: Patel, L., Kraft, P., Guestrin, C., & Zaharia, M. (2024). ACORN: Performant and Predicate-Agnostic Search over Vector Embeddings and Structured Data. SIGMOD 2024. | E43: DSIC27-01, DSIC28-02, DSIC28-05, DSIC30-02, DSIC30-07 | F43: Belum
A44: T24 | B44: Terbaru | C44: Survey of Filtered Approximate Nearest Neighbor Search over the Vector-Scalar Hybrid Data. (2025). arXiv:2505.06501. | E44: DSIC27-01, DSIC28-02, DSIC28-05, DSIC28-07, DSIC30-01, DSIC30-02, DSIC30-03 | F44: Belum
A45: T25 | B45: Terbaru | C45: Malkov, Y. A., & Yashunin, D. A. (2020). Efficient and Robust Approximate Nearest Neighbor Search Using Hierarchical Navigable Small World Graphs. IEEE TPAMI, 42(4), 824–836. | E45: DSIC27-01, DSIC28-02, DSIC28-06, DSIC30-03, DSIC30-06 | F45: Belum
... A59: T39 | B59: Terbaru | C59: Edge-Cloud Collaborative Computing on Distributed Intelligence and Model Optimization: A Survey. (2025). arXiv:2505.01821. | E59: DSIC30-04, DSIC30-08 | F59: Belum
A60: DRV-001 | B60: Drive PDF | C60: Blockchain Tethered AI Trackable, Traceable Artificial Intelligence and Machine Learning (Karen Kilroy, Lynn Riley, Deepak Bhatta) (1).pdf | D60: https://drive.google.com/file/d/1agCn85NNmm3km9gKeZOT9xa6hJ0l7Syb/view?usp=drivesdk | F60: Belum | G60: Folder: Ardika-Pustaka / Block-chain | Diubah: 2026-06-14 12:53
A61: DRV-002 | B61: Drive PDF | C61: Blockchain Tethered AI Trackable, Traceable Artificial Intelligence and Machine Learning (Karen Kilroy, Lynn Riley, Deepak Bhatta) .pdf | D61: https://drive.google.com/file/d/1Nw9UVqo2at4HFLRo7akvDChDHSdDy9Fm/view?usp=drivesdk | F61: Belum | G61: Folder: Ardika-Pustaka / Block-chain | Diubah: 2026-06-14 12:37
A62: DRV-003 | B62: Drive PDF | C62: Data Warehouse and Data Mining Concepts, techniques and real life applications (Jugnesh Kumar) .pdf | D62: https://drive.google.com/file/d/1PXpVEtQLC0MOwZFO44vNWkL_b5sWBBpR/view?usp=drivesdk | F62: Belum | G62: Folder: Ardika-Pustaka / Data Warehouse | Diubah: 2026-08-21 08:29
A63: DRV-004 | B63: Drive PDF | C63: Data Warehouse Learn in 1 day (Krishna Rungta) .pdf | D63: https://drive.google.com/file/d/13l-TuBhxRbHhgkXloXcHa4VHkZK1wFlO/view?usp=drivesdk | F63: Belum | G63: Folder: Ardika-Pustaka / Data Warehouse | Diubah: 2026-08-21 08:32
A64: DRV-005 | B64: Drive PDF | C64: Data Warehouses and OLAP Concepts, Architectures and Solutions (Robert Wrembel etc.) .pdf | D64: https://drive.google.com/file/d/1xtoMfoNd0XrZevJEzCvrDb5Z-gH3GPH1/view?usp=drivesdk | F64: Belum | G64: Folder: Ardika-Pustaka / Data Warehouse | Diubah: 2026-08-21 08:33
A65: DRV-006 | B65: Drive PDF | C65: Data Warehousing Fundamentals for IT Professionals, Second Edition (Paulraj Ponniah) .pdf | D65: https://drive.google.com/file/d/13ay1ac326UqFdXfEuzzNOyndY0KOmSlx/view?usp=drivesdk | F65: Belum | G65: Folder: Ardika-Pustaka / Data Warehouse | Diubah: 2026-08-21 08:34
A66: DRV-007 | B66: Drive PDF | C66: Modernizing SAP Business Warehouse A Strategic Guidance to Migrating to SAP Business Data Cloud (SAP Datasphere and SAP… (Sourav Banerjee) .pdf | D66: https://drive.google.com/file/d/17vS82JO9MSPQoe7NM_hO_90h86zALMcz/view?usp=drivesdk | F66: Belum | G66: Folder: Ardika-Pustaka / Data Warehouse | Diubah: 2026-08-21 08:33
A67: DRV-008 | B67: Drive PDF | C67: Snowflake Data Warehouse Engineering Architecture, Modeling, ELT Pipelines, and Operations (Martin Hander) .pdf | D67: https://drive.google.com/file/d/1_xFKSAnpMKIXRpZR9AUNWa2zUIedH-MS/view?usp=drivesdk | F67: Belum | G67: Folder: Ardika-Pustaka / Data Warehouse | Diubah: 2026-08-21 08:30
A68: DRV-009 | B68: Drive PDF | C68: Advanced Analytics with PySpark Patterns for Learning from Data at Scale Using Python and Spark (Akash Tandon, Sandy Ryza, Uri Laserson etc.) .pdf | D68: https://drive.google.com/file/d/1VHgBasQZ0IKHn8imUyvAsaTqhcuhMPsa/view?usp=drivesdk | F68: Belum | G68: Folder: Ardika-Pustaka / Data-engineering | Diubah: 2026-06-14 08:42
A69: DRV-010 | B69: Drive PDF | C69: AI-Powered Business Intelligence Improving Forecasts and Decision Making with Machine Learning (Tobias Zwingmann) .pdf | D69: https://drive.google.com/file/d/1tNXFzMNq5cOjGEQHe8sRz0GhrKfSDCT9/view?usp=drivesdk | F69: Belum | G69: Folder: Ardika-Pustaka / Data-engineering | Diubah: 2026-06-14 08:45
A70: DRV-011 | B70: Drive PDF | C70: Analytics Engineering with SQL and dbt Building Meaningful Data Models at Scale (Rui Pedro Machado, Helder Russa) .pdf | D70: https://drive.google.com/file/d/1DziuJ4rL3lGbVwMU7TKr8zI7OGgo_mOn/view?usp=drivesdk | F70: Belum | G70: Folder: Ardika-Pustaka / Data-engineering | Diubah: 2026-06-14 12:10
A71: DRV-012 | B71: Drive PDF | C71: Apache Hudi The Definitive Guide (Shiyan Xu, Prashant Wason etc.) .pdf | D71: https://drive.google.com/file/d/1zGj1zW6e69oRbuRxsgVKvOA37d1AYJgc/view?usp=drivesdk | F71: Belum | G71: Folder: Ardika-Pustaka / Data-engineering | Diubah: 2026-06-15 21:10
... A202: DRV-143 | B202: Drive PDF | C202: Trino The Definitive Guide SQL at Any Scale, on Any Storage, in Any Environment, 2nd Edition (Matt Fuller, Manfred Moser, Martin Traverso) .pdf | D202: https://drive.google.com/file/d/1AE7fWYWmmhMp6fZ1shBETts2wAw4PwdT/view?usp=drivesdk | F202: Belum | G202: Folder: Ardika-Pustaka | Diubah: 2026-06-15 16:30

Sheet 123450063
A1: LOGBOOK BIMBINGAN TUGAS AKHIR — DSIC RESEARCH GROUP
A2: NIM | C2: 123450063 | E2: Nama | G2: ARYA MUDA SIREGAR
A3: Pertemuan selesai | C3: =COUNTIF(L25:L38,"Selesai") -> 1 | D3: Terverifikasi | F3: =COUNTIF(M25:M38,TRUE) -> 1 | G3: Progress | I3: =COUNTIF(L25:L38,"Selesai")/14 -> 0.071428571 | J3: Status topik | L3: =G5 -> Disetujui
A4: A. USULAN DAN PENETAPAN TOPIK
A5: Sumber Topik Final | C5: Katalog DSIC | E5: Status Topik | G5: Disetujui | I5: Tanggal Penetapan | K5: 46269
A6: Kode Topik Katalog | C6: DSIC30-07 | E6: Jalur Kelulusan | G6: Artikel Ilmiah | I6: Link Folder / Repo | K6: https://drive.google.com/drive/folders/1WVaSsnFzzWYyZERbwYCX6sJut6CFFidv?usp=sharing
A7: Judul dari Katalog | C7: {=IFERROR(INDEX(KATALOG_TOPIK!$D:$D,MATCH($C$6,KATALOG_TOPIK!$A:$A,0)),"")} -> LLM yang Hanya Boleh Memakai Data Tepercaya
A8: Pertanyaan Penelitian Katalog | C8: {=IFERROR(INDEX(KATALOG_TOPIK!$E:$E,MATCH($C$6,KATALOG_TOPIK!$A:$A,0)),"")} -> Dapatkah sebuah LLM dibatasi agar hanya memakai data yang memenuhi syarat keyakinan dan asal-usul tertentu, tanpa kehilangan terlalu banyak pertanyaan yang bisa dijawab?
A9: Dataset Katalog | C9: {=IFERROR(INDEX(KATALOG_TOPIK!$I:$I,MATCH($C$6,KATALOG_TOPIK!$A:$A,0)),"")} -> Koleksi dokumen berlabel sumber dan tingkat keyakinan.
A10: Pembanding / Baseline Katalog | C10: {=IFERROR(INDEX(KATALOG_TOPIK!$G:$G,MATCH($C$6,KATALOG_TOPIK!$A:$A,0)),"")} -> LLM tanpa pembatasan sumber.
A11: Kebaruan Katalog | C11: {=IFERROR(INDEX(KATALOG_TOPIK!$H:$H,MATCH($C$6,KATALOG_TOPIK!$A:$A,0)),"")} -> Antarmuka agent dengan pagar pengaman yang ditegakkan oleh sistem data, bukan oleh prompt.
A12: Judul Usulan Mahasiswa | C12: Kepentingan Expert yang Bergantung pada Intervensi dalam Model Bahasa Mixture-of-Experts
A13: Pertanyaan Penelitian Usulan | C13: 1. Seberapa besar pengaruh sebuah expert terhadap prediksi model ketika expert tersebut diintervensi secara langsung?, 2. Apakah penilaian terhadap pentingnya sebuah expert berubah ketika expert yang sama dihilangkan dengan cara intervensi yang berbeda?
A14: Dataset Usulan | C14: C4 Validation
A15: Pembanding / Baseline Usulan | C15: Model tanpa intervensi, lalu dibandingkan dengan zero-output ablation, survivor reweighting, dan native rerouting pada expert-token-layer event yang sama.
A16: Kebaruan / Gap Usulan | C16: Studi sebelumnya telah mengkaji expert ablation, removal, dan counterfactual routing, tetapi belum secara eksplisit menguji kestabilan kepentingan kausal expert melalui beberapa bentuk intervensi yang diterapkan secara berpasangan pada expert, token, dan layer yang sama.
A17: Metrik Keberhasilan | C17: delta Negative Log-Likelihood(NLL), kestabilan peringkat expert antarintervensi, rank reversal, dan top-expert overlap.
A18: Judul Final | C18: =IF($C$5="Katalog DSIC",$C$7,IF($C$5="Usulan Mahasiswa",$C$12,"")) -> LLM yang Hanya Boleh Memakai Data Tepercaya
A19: Pertanyaan Penelitian Final | C19: =IF($C$5="Katalog DSIC",$C$8,IF($C$5="Usulan Mahasiswa",$C$13,"")) -> Dapatkah sebuah LLM dibatasi agar hanya memakai data yang memenuhi syarat keyakinan dan asal-usul tertentu, tanpa kehilangan terlalu banyak pertanyaan yang bisa dijawab?
A20: Catatan Penetapan Pembimbing | C20: Audit-DSIC3007.pdf
A23: B. LOGBOOK 14 PERTEMUAN
A24: No | B24: Kode | C24: Tahap | D24: Fokus Pertemuan | E24: Tanggal | F24: Mode | G24: Durasi (menit) | H24: Yang Dilaporkan Mahasiswa | I24: Arahan & Catatan Pembimbing | J24: Target Pertemuan Berikutnya | K24: Link Artefak | L24: Status | M24: Verifikasi
A25: 1 | B25: P1 | C25: Bulan 1 | D25: Penetapan topik dan pertanyaan penelitian | E25: 46269 | F25: Luring | G25: 120 menit | H25: Menerapkan topik berdasarkan katalog DSIC30-07 serta menyusun 2 pertanyaan penelitian: 1. Seberapa besar pengaruh sebuah expert terhadap prediksi model ketika expert tersebut diintervensi secara langsung?, 2. Apakah penilaian terhadap pentingnya sebuah expert berubah ketika expert yang sama dihilangkan dengan cara intervensi yang berbeda? | I25: Tambahkan lebih banyak artikel di topik tersebut dan lebih di tentukan domainnya | J25: Dataset, pembanding, dan ukuran keberhasilan | K25: Drive | L25: Selesai | M25: TRUE
A26: 2 | B26: P2 | C26: Bulan 1 | D26: Dataset, pembanding, dan ukuran keberhasilan | L26: Belum Dilaksanakan | M26: FALSE
A27: 3 | B27: P3 | C27: Bulan 1 | D27: Rencana eksperimen dan protokol pengukuran | L27: Belum Dilaksanakan | M27: FALSE
A28: 4 | B28: P4 | C28: Bulan 2 | D28: Hasil pembanding pertama | L28: Belum Dilaksanakan | M28: FALSE
A29: 5 | B29: P5 | C29: Bulan 2 | D29: Kesiapan data dan pipeline eksperimen | L29: Belum Dilaksanakan | M29: FALSE
A30: 6 | B30: P6 | C30: Bulan 2 | D30: Eksperimen utama, gelombang pertama | L30: Belum Dilaksanakan | M30: FALSE
A31: 7 | B31: P7 | C31: Bulan 3 | D31: Eksperimen utama, gelombang kedua | L31: Belum Dilaksanakan | M31: FALSE
A32: 8 | B32: P8 | C32: Bulan 3 | D32: Tinjauan hasil sementara dan koreksi arah | L32: Belum Dilaksanakan | M32: FALSE
A33: 9 | B33: P9 | C33: Bulan 3 | D33: Analisis hasil dan penyusunan tabel serta grafik | L33: Belum Dilaksanakan | M33: FALSE
A34: 10 | B34: P10 | C34: Bulan 4 | D34: Penutupan penelitian dan verifikasi keterulangan | L34: Belum Dilaksanakan | M34: FALSE
A35: 11 | B35: P11 | C35: Bulan 4 | D35: Kerangka naskah dan bab metode | L35: Belum Dilaksanakan | M35: FALSE
A36: 12 | B36: P12 | C36: Bulan 4 | D36: Bab hasil dan pembahasan | L36: Belum Dilaksanakan | M36: FALSE
A37: 13 | B37: P13 | C37: Bulan 4 | D37: Draf lengkap dan tinjauan menyeluruh | L37: Belum Dilaksanakan | M37: FALSE
A38: 14 | B38: P14 | C38: Bulan 4 | D38: Finalisasi dan kesiapan seminar atau sidang | L38: Belum Dilaksanakan | M38: FALSE
A41: C. CHECKLIST ARTEFAK MINIMUM
A42: No | B42: Artefak | C42: Link / Lokasi | D42: Selesai
A43: 1 | B43: Ringkasan masalah dan pertanyaan penelitian (1 halaman) | D43: FALSE
A44: 2 | B44: Daftar sumber dataset dan versi data | D44: FALSE
A45: 3 | B45: Kode atau notebook eksperimen | D45: FALSE
A46: 4 | B46: Catatan konfigurasi dan langkah menjalankan ulang | D46: FALSE
A47: 5 | B47: Hasil pembanding / baseline | D47: FALSE
A48: 6 | B48: Hasil eksperimen utama | D48: FALSE
A49: 7 | B49: Tabel atau grafik yang menjawab pertanyaan penelitian | D49: FALSE
A50: 8 | B50: Kesimpulan penelitian | D50: FALSE
A51: 9 | B51: Draf skripsi atau draf artikel ilmiah | D51: FALSE

Sheet 123450104
A1: LOGBOOK BIMBINGAN TUGAS AKHIR — DSIC RESEARCH GROUP
A2: NIM | C2: 123450104 | E2: Nama | G2: Fabio Banyu Cyto
A3: Pertemuan selesai | C3: =COUNTIF(L25:L38,"Selesai") -> 2 | D3: Terverifikasi | F3: =COUNTIF(M25:M38,TRUE) -> 2 | G3: Progress | I3: =COUNTIF(L25:L38,"Selesai")/14 -> 0.14285714 | J3: Status topik | L3: =G5 -> Disetujui
A4: A. USULAN DAN PENETAPAN TOPIK
A5: Sumber Topik Final | C5: Katalog DSIC | E5: Status Topik | G5: Disetujui | I5: Tanggal Penetapan | K5: 46270
A6: Kode Topik Katalog | C6: DSIC27-06 | E6: Jalur Kelulusan | G6: Skripsi Tradisional | I6: Link Folder / Repo | K6: https://github.com/Data-Systems-and-Intelligent-Computing/DSIC-2706 / TUGAS AKHIR
A7: Judul dari Katalog | C7: {=IFERROR(INDEX(KATALOG_TOPIK!$D:$D,MATCH($C$6,KATALOG_TOPIK!$A:$A,0)),"")} -> Mencari Audio yang Mirip Ketika Datanya Terbatas
A8: Pertanyaan Penelitian Katalog | C8: {=IFERROR(INDEX(KATALOG_TOPIK!$E:$E,MATCH($C$6,KATALOG_TOPIK!$A:$A,0)),"")} -> Representasi audio mana yang paling tahan terhadap derau lingkungan ketika dipakai untuk menemukan rekaman lain dengan karakter suara serupa?
A9: Dataset Katalog | C9: {=IFERROR(INDEX(KATALOG_TOPIK!$I:$I,MATCH($C$6,KATALOG_TOPIK!$A:$A,0)),"")} -> ESC-50 sebagai dataset utama; subset BirdCLEF bila ingin lebih dekat ke bioakustik.
A10: Pembanding / Baseline Katalog | C10: {=IFERROR(INDEX(KATALOG_TOPIK!$G:$G,MATCH($C$6,KATALOG_TOPIK!$A:$A,0)),"")} -> MFCC dengan jarak kosinus.
A11: Kebaruan Katalog | C11: {=IFERROR(INDEX(KATALOG_TOPIK!$H:$H,MATCH($C$6,KATALOG_TOPIK!$A:$A,0)),"")} -> Menguji ketahanan representasi terhadap derau dan pergeseran kondisi perekaman, bukan hanya akurasi pada data bersih.
A12: Judul Usulan Mahasiswa | C12: Ketahanan Representasi Audio terhadap Derau dan Pergeseran Domain untuk Pencarian Kemiripan Bioakustik: Studi Xeno-Canto ke Soundscape ITERA
A13: Pertanyaan Penelitian Usulan | C13: 1. Representasi audio mana yang mempertahankan kualitas similarity retrieval paling baik ketika query bioakustik mengalami peningkatan derau lingkungan dan pergeseran domain dari focal recording ke soundscape? 2. Seberapa besar penurunan kualitas retrieval (mAP@k dan Recall@k) pada beberapa tingkat SNR dan ketika berpindah dari focal recording ke soundscape nyata? 3. Apakah threshold similarity yang dikalibrasi pada data terpisah tetap mampu menolak audio unknown/background tanpa meningkatkan false positive secara berlebihan ketika noise dan domain perekaman berubah? 4. Apakah bioacoustic-specific embedding memiliki robustness retention yang lebih baik daripada generic audio embedding dan MFCC pada kondisi noise yang sama? 5. Candidate match spesies apa yang muncul pada subset soundscape ITERA yang telah diverifikasi manual? (sekunder)
A14: Dataset Usulan | C14: Reference/gallery: subset Xeno-Canto untuk 10–20 spesies burung target Sumatera (manifest mencakup recording ID, perekam, lokasi, tanggal, kualitas, lisensi, dan checksum; split gallery/query berbasis recording ID, idealnya recordist-disjoint). Controlled noise: rekaman background-only ITERA dari minimal tiga lokasi (Embung, Arboretum/Kebun Raya, area terbuka/antropogenik) pada beberapa waktu berbeda. External validation: subset kecil soundscape ITERA nyata yang dianotasi manual. ESC-50 dan subset BirdCLEF/BirdSet dipakai hanya sebagai sanity check/validasi eksternal opsional, bukan dataset utama.
A15: Pembanding / Baseline Usulan | C15: Baseline: MFCC + cosine similarity (frozen, tanpa fine-tuning). Pembanding: maksimum dua deep representation froze, satu generic pretrained audio embedding (PANNs) dan satu bioacoustic-specific embedding (salah satu dari BirdNET/Global Birdsong Embeddings/ConvNeXt yang checkpoint-nya paling stabil), diukur dengan cosine similarity yang sama. Random ranking ditambahkan sebagai kontrol negatif.
A16: Kebaruan / Gap Usulan | C16: Kebaruan tidak diklaim pada penggunaan Xeno-Canto, BirdNET/PANNs, atau cross-domain focal-to-soundscape secara individual, karena hal-hal tersebut sudah muncul. Kontribusi penelitian ditempatkan pada desain evaluasi paired robustness: representasi hand-crafted, generic pretrained, dan bioacoustic pretrained dibandingkan pada query yang sama di beberapa tingkat SNR menggunakan background noise ITERA, lalu diuji ulang pada soundscape nyata dengan threshold open-set yang dikalibrasi pada split terpisah dan diuji stabilitasnya (threshold transfer), menghasilkan local cross-domain benchmark Sumatra–ITERA yang reproducible.
A17: Metrik Keberhasilan | C17: 1. Endpoint retrieval primer: mAP@k, Recall@k (Recall@1/5/10), dan Precision@k. 2. Endpoint robustness: mAP@k mentah pada kondisi bersih dan setiap tingkat SNR (20, 10, 0, −5 dB), beserta penurunan absolut/relatif terhadap kondisi bersih. 3. Endpoint open-set: AUPRC, AUROC, F1 pada threshold hasil kalibrasi, serta false-positive/false-accept rate. 4. Metrik sekunder: top-1 accuracy dan tingkat verifikasi manual pada candidate match soundscape ITERA. 5. t-SNE/UMAP hanya dipakai sebagai visualisasi pendukung, bukan kriteria keberhasilan.
A18: Judul Final | C18: =IF($C$5="Katalog DSIC",$C$7,IF($C$5="Usulan Mahasiswa",$C$12,"")) -> Mencari Audio yang Mirip Ketika Datanya Terbatas
A19: Pertanyaan Penelitian Final | C19: =IF($C$5="Katalog DSIC",$C$8,IF($C$5="Usulan Mahasiswa",$C$13,"")) -> Representasi audio mana yang paling tahan terhadap derau lingkungan ketika dipakai untuk menemukan rekaman lain dengan karakter suara serupa?
A20: Catatan Penetapan Pembimbing | C20: Silahkan di lanjutkan Audit-DSIC-2706-Revisi-Bioacoustic-Retrieval.pdf Audit-DSIC-2706-Keputusan-Kedua-2026.pdf
A23: B. LOGBOOK 14 PERTEMUAN
A24: No | B24: Kode | C24: Tahap | D24: Fokus Pertemuan | E24: Tanggal | F24: Mode | G24: Durasi (menit) | H24: Yang Dilaporkan Mahasiswa | I24: Arahan & Catatan Pembimbing | J24: Target Pertemuan Berikutnya | K24: Link Artefak | L24: Status | M24: Verifikasi
A25: 1 | B25: P1 | C25: Bulan 1 | D25: Penetapan topik dan pertanyaan penelitian | E25: 46269 | F25: Luring | G25: 120 menit | H25: Menetapkan Topik Katalog DSIC27-06 dengan mencari research question, arah penelitian, dan referensi jurnal | K25: https://github.com/Data-Systems-and-Intelligent-Computing/DSIC-2706/tree/main/jurnal | L25: Selesai | M25: TRUE
A26: 2 | B26: P2 | C26: Bulan 1 | D26: Dataset, pembanding, dan ukuran keberhasilan | E26: 46272 | F26: Daring | G26: 30 menit | H26: 1. Dataset: Mengumpulkan 416 audio burung target (16 takson) dari Xeno-Canto dan 77 audio satwa non-burung untuk uji open-set. Preprocessing dibekukan pada 32 kHz mono, segmen 5.0 detik, dan RMS 0.05. 2. Partisi Bebas Kebocoran: Menerapkan Strict Recordist-Disjoint (Galeri 42 perekam, Query 29 perekam) dengan irisan tepat 0 perekam (Zero Leakage). 3. Pembanding (Representasi): Menyiapkan 4 model pembanding, yaitu R0 (MFCC), R1 (Generic PANNs), R2 (Bioacoustic Pretrained), dan R3 (Random Gaussian Control). 4. Ukuran Keberhasilan: Menetapkan metrik mAP@10, kurva retensi performa relatif lintas level derau (Clean s/d -5 dB SNR), serta optimalisasi ambang batas Youden's J (tau*) untuk penolakan audio asing. | K26: https://github.com/Data-Systems-and-Intelligent-Computing/DSIC-2706/tree/main/Rencana-eksperimen/minggu-1 | L26: Selesai | M26: TRUE
A27: 3 | B27: P3 | C27: Bulan 1 | D27: Rencana eksperimen dan protokol pengukuran | L27: Belum Dilaksanakan | M27: FALSE
A28: 4 | B28: P4 | C28: Bulan 2 | D28: Hasil pembanding pertama | L28: Belum Dilaksanakan | M28: FALSE
A29: 5 | B29: P5 | C29: Bulan 2 | D29: Kesiapan data dan pipeline eksperimen | L29: Belum Dilaksanakan | M29: FALSE
A30: 6 | B30: P6 | C30: Bulan 2 | D30: Eksperimen utama, gelombang pertama | L30: Belum Dilaksanakan | M30: FALSE
A31: 7 | B31: P7 | C31: Bulan 3 | D31: Eksperimen utama, gelombang kedua | L31: Belum Dilaksanakan | M31: FALSE
A32: 8 | B32: P8 | C32: Bulan 3 | D32: Tinjauan hasil sementara dan koreksi arah | L32: Belum Dilaksanakan | M32: FALSE
A33: 9 | B33: P9 | C33: Bulan 3 | D33: Analisis hasil dan penyusunan tabel serta grafik | L33: Belum Dilaksanakan | M33: FALSE
A34: 10 | B34: P10 | C34: Bulan 4 | D34: Penutupan penelitian dan verifikasi keterulangan | L34: Belum Dilaksanakan | M34: FALSE
A35: 11 | B35: P11 | C35: Bulan 4 | D35: Kerangka naskah dan bab metode | L35: Belum Dilaksanakan | M35: FALSE
A36: 12 | B36: P12 | C36: Bulan 4 | D36: Bab hasil dan pembahasan | L36: Belum Dilaksanakan | M36: FALSE
A37: 13 | B37: P13 | C37: Bulan 4 | D37: Draf lengkap dan tinjauan menyeluruh | L37: Belum Dilaksanakan | M37: FALSE
A38: 14 | B38: P14 | C38: Bulan 4 | D38: Finalisasi dan kesiapan seminar atau sidang | L38: Belum Dilaksanakan | M38: FALSE
A41: C. CHECKLIST ARTEFAK MINIMUM
A42: No | B42: Artefak | C42: Link / Lokasi | D42: Selesai
A43: 1 | B43: Ringkasan masalah dan pertanyaan penelitian (1 halaman) | C43: Jurnal: https://github.com/Data-Systems-and-Intelligent-Computing/DSIC-2706/tree/main/jurnal Ringkasan Referensi: https://github.com/Data-Systems-and-Intelligent-Computing/DSIC-2706/blob/main/jurnal/referensi_jurnal_TA_bioakustik.csv | D43: TRUE
A44: 2 | B44: Daftar sumber dataset dan versi data | C44: Sumber: https://xeno-canto.org/explore/region Dataset: https://github.com/Data-Systems-and-Intelligent-Computing/DSIC-2706/tree/main/data | D44: TRUE
A45: 3 | B45: Kode atau notebook eksperimen | D45: FALSE
A46: 4 | B46: Catatan konfigurasi dan langkah menjalankan ulang | D46: FALSE
A47: 5 | B47: Hasil pembanding / baseline | D47: FALSE
A48: 6 | B48: Hasil eksperimen utama | D48: FALSE
A49: 7 | B49: Tabel atau grafik yang menjawab pertanyaan penelitian | D49: FALSE
A50: 8 | B50: Kesimpulan penelitian | D50: FALSE
A51: 9 | B51: Draf skripsi atau draf artikel ilmiah | D51: FALSE

Sheet 123450114
A1: LOGBOOK BIMBINGAN TUGAS AKHIR — DSIC RESEARCH GROUP
A2: NIM | C2: 123450114 | E2: Nama | G2: Desman Velius Halawa
A3: Pertemuan selesai | C3: =COUNTIF(L25:L38,"Selesai") -> 2 | D3: Terverifikasi | F3: =COUNTIF(M25:M38,TRUE) -> 2 | G3: Progress | I3: =COUNTIF(L25:L38,"Selesai")/14 -> 0.14285714 | J3: Status topik | L3: =G5 -> Disetujui
A4: A. USULAN DAN PENETAPAN TOPIK
A5: Sumber Topik Final | C5: Katalog DSIC | E5: Status Topik | G5: Disetujui | I5: Tanggal Penetapan | K5: 46271
A6: Kode Topik Katalog | C6: DSIC26-04 | E6: Jalur Kelulusan | G6: Artikel Ilmiah | I6: Link Folder / Repo | K6: https://drive.google.com/drive/folders/1eIgh5ct1UR1qCWrG2AxvNm8qDuD5zjJ9?usp=sharing
A7: Judul dari Katalog | C7: {=IFERROR(INDEX(KATALOG_TOPIK!$D:$D,MATCH($C$6,KATALOG_TOPIK!$A:$A,0)),"")} -> Ukuran Berkas Parquet yang Pas untuk Lakehouse Kecil
A8: Pertanyaan Penelitian Katalog | C8: {=IFERROR(INDEX(KATALOG_TOPIK!$E:$E,MATCH($C$6,KATALOG_TOPIK!$A:$A,0)),"")} -> Ukuran berkas berapa, dan pembagian data seperti apa, yang paling sesuai untuk kombinasi pemasukan data dan query analitik pada klaster kecil?
A9: Dataset Katalog | C9: {=IFERROR(INDEX(KATALOG_TOPIK!$I:$I,MATCH($C$6,KATALOG_TOPIK!$A:$A,0)),"")} -> NYC TLC Trip Record Data dalam format Parquet, atau dataset tabular publik lain yang sudah disiapkan.
A10: Pembanding / Baseline Katalog | C10: {=IFERROR(INDEX(KATALOG_TOPIK!$G:$G,MATCH($C$6,KATALOG_TOPIK!$A:$A,0)),"")} -> Ukuran tetap 128 MB, 256 MB, dan 512 MB.
A11: Kebaruan Katalog | C11: {=IFERROR(INDEX(KATALOG_TOPIK!$H:$H,MATCH($C$6,KATALOG_TOPIK!$A:$A,0)),"")} -> Kebijakan ukuran berkas diturunkan dari beban kerja dan keterbatasan perangkat keras yang benar-benar ada.
A12: Judul Usulan Mahasiswa | C12: Penentuan Ukuran Berkas Parquet Optimal Berbasis Profil Beban Kerja Campuran pada Lingkungan Lakehouse Skala Kecil / A Controlled Evaluation of Parquet File Size and Query Selectivity in Resource-Constrained Lakehouses
A13: Pertanyaan Penelitian Usulan | C13: Bagaimana ukuran berkas Parquet yang berbeda memengaruhi query latency pada tingkat query selectivity yang berbeda dalam resource-constrained lakehouse, dan apakah terdapat kondisi tertentu ketika ukuran berkas yang lebih kecil atau lebih besar menjadi lebih menguntungkan?
A14: Dataset Usulan | C14: Dataset tabular berukuran besar dari Data in Brief, diutamakan data smart meter/energy consumption, traffic, atau sensor time-series yang memiliki atribut waktu, identifier entitas, dan variabel numerik sehingga memungkinkan pembentukan query dengan tingkat selectivity yang berbeda secara alami. Bisa gunakan ini: https://www.sciencedirect.com/science/article/pii/S2352340926001824
A15: Pembanding / Baseline Usulan | C15: Ukuran berkas Parquet tetap, misalnya 32 MB, 64 MB, 128 MB, dan 256 MB, dengan 128 MB sebagai baseline utama. Seluruh konfigurasi lain seperti hardware, query engine, partitioning, compression, dan dataset dibuat tetap.
A16: Kebaruan / Gap Usulan | C16: Studi tidak hanya membandingkan ukuran file secara terpisah, tetapi mengevaluasi secara terkontrol interaksi antara Parquet file size dan query selectivity pada lingkungan lakehouse dengan sumber daya terbatas. Fokusnya adalah mengidentifikasi performance crossover point, yaitu kondisi selectivity ketika keuntungan kinerja berpindah dari file kecil ke file besar atau sebaliknya.
A17: Metrik Keberhasilan | C17: p50 dan p95 query latency sebagai metrik utama; didukung oleh bytes scanned, number of files scanned, CPU utilization, peak memory usage, dan bila diperlukan query throughput. Keberhasilan penelitian ditunjukkan oleh adanya pola atau crossover yang konsisten dan dapat direproduksi antar-pengulangan eksperimen.
A18: Judul Final | C18: =IF($C$5="Katalog DSIC",$C$7,IF($C$5="Usulan Mahasiswa",$C$12,"")) -> Ukuran Berkas Parquet yang Pas untuk Lakehouse Kecil
A19: Pertanyaan Penelitian Final | C19: =IF($C$5="Katalog DSIC",$C$8,IF($C$5="Usulan Mahasiswa",$C$13,"")) -> Ukuran berkas berapa, dan pembagian data seperti apa, yang paling sesuai untuk kombinasi pemasukan data dan query analitik pada klaster kecil?
A20: Catatan Penetapan Pembimbing | C20: Audit-DSIC-2604-Parquet-File-Size-Selectivity.pdf Protokol lab: Protokol-dan-Teknis-Lab-DSIC-2606.pdf
A23: B. LOGBOOK 14 PERTEMUAN
A24: No | B24: Kode | C24: Tahap | D24: Fokus Pertemuan | E24: Tanggal | F24: Mode | G24: Durasi (menit) | H24: Yang Dilaporkan Mahasiswa | I24: Arahan & Catatan Pembimbing | J24: Target Pertemuan Berikutnya | K24: Link Artefak | L24: Status | M24: Verifikasi
A25: 1 | B25: P1 | C25: Bulan 1 | D25: Penetapan topik dan pertanyaan penelitian | E25: 46271 | F25: Luring | G25: 120 Menit | H25: Menerapkan topik berdasarkan katalog DSIC26-04 serta menentukan judull usulan mahaisiswa : Penentuan Ukuran Berkas Parquet Optimal Berbasis Profil Beban Kerja Campuran pada Lingkungan Lakehouse Skala Kecil | I25: 1. Mencari dataset tambahan di | J25: 1. Dataset dan Jurnal 2. 11 September 2026 | K25: https://drive.google.com/drive/folders/1eIgh5ct1UR1qCWrG2AxvNm8qDuD5zjJ9?usp=sharing | L25: Selesai | M25: TRUE
A26: 2 | B26: P2 | C26: Bulan 1 | D26: Dataset, pembanding, dan ukuran keberhasilan | E26: 46273 | F26: Luring | H26: Mengerjakan step minggu 1 (H1). | I26: 1. Lanjut H2 dan H3 | J26: 46276 | L26: Selesai | M26: TRUE
A27: 3 | B27: P3 | C27: Bulan 1 | D27: Rencana eksperimen dan protokol pengukuran | L27: Belum Dilaksanakan | M27: FALSE
A28: 4 | B28: P4 | C28: Bulan 2 | D28: Hasil pembanding pertama | L28: Belum Dilaksanakan | M28: FALSE
A29: 5 | B29: P5 | C29: Bulan 2 | D29: Kesiapan data dan pipeline eksperimen | L29: Belum Dilaksanakan | M29: FALSE
A30: 6 | B30: P6 | C30: Bulan 2 | D30: Eksperimen utama, gelombang pertama | L30: Belum Dilaksanakan | M30: FALSE
A31: 7 | B31: P7 | C31: Bulan 3 | D31: Eksperimen utama, gelombang kedua | L31: Belum Dilaksanakan | M31: FALSE
A32: 8 | B32: P8 | C32: Bulan 3 | D32: Tinjauan hasil sementara dan koreksi arah | L32: Belum Dilaksanakan | M32: FALSE
A33: 9 | B33: P9 | C33: Bulan 3 | D33: Analisis hasil dan penyusunan tabel serta grafik | L33: Belum Dilaksanakan | M33: FALSE
A34: 10 | B34: P10 | C34: Bulan 4 | D34: Penutupan penelitian dan verifikasi keterulangan | L34: Belum Dilaksanakan | M34: FALSE
A35: 11 | B35: P11 | C35: Bulan 4 | D35: Kerangka naskah dan bab metode | L35: Belum Dilaksanakan | M35: FALSE
A36: 12 | B36: P12 | C36: Bulan 4 | D36: Bab hasil dan pembahasan | L36: Belum Dilaksanakan | M36: FALSE
A37: 13 | B37: P13 | C37: Bulan 4 | D37: Draf lengkap dan tinjauan menyeluruh | L37: Belum Dilaksanakan | M37: FALSE
A38: 14 | B38: P14 | C38: Bulan 4 | D38: Finalisasi dan kesiapan seminar atau sidang | L38: Belum Dilaksanakan | M38: FALSE
A41: C. CHECKLIST ARTEFAK MINIMUM
A42: No | B42: Artefak | C42: Link / Lokasi | D42: Selesai
A43: 1 | B43: Ringkasan masalah dan pertanyaan penelitian (1 halaman) | D43: FALSE
A44: 2 | B44: Daftar sumber dataset dan versi data | D44: FALSE
A45: 3 | B45: Kode atau notebook eksperimen | D45: FALSE
A46: 4 | B46: Catatan konfigurasi dan langkah menjalankan ulang | D46: FALSE
A47: 5 | B47: Hasil pembanding / baseline | D47: FALSE
A48: 6 | B48: Hasil eksperimen utama | D48: FALSE
A49: 7 | B49: Tabel atau grafik yang menjawab pertanyaan penelitian | D49: FALSE
A50: 8 | B50: Kesimpulan penelitian | D50: FALSE
A51: 9 | B51: Draf skripsi atau draf artikel ilmiah | D51: FALSE

Sheet 123450039
A1: LOGBOOK BIMBINGAN TUGAS AKHIR — DSIC RESEARCH GROUP
A2: NIM | C2: 123450039 | E2: Nama | G2: FEBY ANGELINA
A3: Pertemuan selesai | C3: =COUNTIF(L25:L38,"Selesai") -> 1 | D3: Terverifikasi | F3: =COUNTIF(M25:M38,TRUE) -> 1 | G3: Progress | I3: =COUNTIF(L25:L38,"Selesai")/14 -> 0.071428571 | J3: Status topik | L3: =G5 -> Disetujui
A4: A. USULAN DAN PENETAPAN TOPIK
A5: Sumber Topik Final | C5: Katalog DSIC | E5: Status Topik | G5: Disetujui | I5: Tanggal Penetapan | K5: 46271
A6: Kode Topik Katalog | C6: DSIC29-06 | E6: Jalur Kelulusan | G6: Artikel Ilmiah | I6: Link Folder / Repo | K6: referensi
A7: Judul dari Katalog | C7: {=IFERROR(INDEX(KATALOG_TOPIK!$D:$D,MATCH($C$6,KATALOG_TOPIK!$A:$A,0)),"")} -> Haruskah Query pada Data Meragukan Diperlakukan Berbeda?
A8: Pertanyaan Penelitian Katalog | C8: {=IFERROR(INDEX(KATALOG_TOPIK!$E:$E,MATCH($C$6,KATALOG_TOPIK!$A:$A,0)),"")} -> Apakah query terhadap data berkualitas rendah sebaiknya diarahkan ke jalur pengambilan atau pemeriksaan yang berbeda?
A9: Dataset Katalog | C9: {=IFERROR(INDEX(KATALOG_TOPIK!$I:$I,MATCH($C$6,KATALOG_TOPIK!$A:$A,0)),"")} -> Snapshot JADESTA/Sigerciv dengan skor kualitas per catatan.
A10: Pembanding / Baseline Katalog | C10: {=IFERROR(INDEX(KATALOG_TOPIK!$G:$G,MATCH($C$6,KATALOG_TOPIK!$A:$A,0)),"")} -> Eksekusi seragam untuk semua query.
A11: Kebaruan Katalog | C11: {=IFERROR(INDEX(KATALOG_TOPIK!$H:$H,MATCH($C$6,KATALOG_TOPIK!$A:$A,0)),"")} -> Keputusan eksekusi yang mempertimbangkan tingkat keyakinan data.
A12: Judul Usulan Mahasiswa | C12: Conflict-Aware Query Routing for Multi-Source Tourism Data / Perutean Query Berbasis Konflik Data pada Integrasi Data Pariwisata Multi-Sumber
A13: Pertanyaan Penelitian Usulan | C13: Apakah perutean query berdasarkan tingkat kesepakatan dan konflik antar-sumber dapat meningkatkan keandalan hasil query dibandingkan eksekusi query yang memperlakukan seluruh data secara seragam?
A14: Dataset Usulan | C14: Data JADESTA sebagai sumber utama, kemudian diperkaya dengan klaim atribut dari 2–3 sumber publik lain, misalnya Wikidata/Wikipedia dan situs resmi pemerintah atau pengelola destinasi. Fokus pada subset sekitar 500–1.000 entitas dan 5–8 atribut seperti nama, lokasi, kategori, fasilitas, kontak, dan status destinasi.
A15: Pembanding / Baseline Usulan | C15: B0 — Uniform Query Execution: seluruh data diperlakukan sama tanpa melihat konflik antar-sumber. B1 — Conflict Filtering: data yang memiliki konflik langsung dikeluarkan dari hasil query.
A16: Kebaruan / Gap Usulan | C16: Sebagian pendekatan integrasi data hanya memilih satu nilai, menghapus data konflik, atau melakukan data cleaning sebelum query. Penelitian ini menguji pendekatan di mana status konflik antar-sumber digunakan pada saat eksekusi query untuk menentukan jalur pengambilan data, misalnya direct retrieval, cross-source verification, atau abstention.
A17: Metrik Keberhasilan | C17: Answer Accuracy, Unsupported Answer Rate, Conflict Exposure Rate, Query Latency, dan Verification Rate. Metode dianggap berhasil jika meningkatkan reliabilitas hasil query dibanding baseline dengan tambahan biaya query yang masih dapat diterima.
A18: Judul Final | C18: =IF($C$5="Katalog DSIC",$C$7,IF($C$5="Usulan Mahasiswa",$C$12,"")) -> Haruskah Query pada Data Meragukan Diperlakukan Berbeda?
A19: Pertanyaan Penelitian Final | C19: =IF($C$5="Katalog DSIC",$C$8,IF($C$5="Usulan Mahasiswa",$C$13,"")) -> Apakah query terhadap data berkualitas rendah sebaiknya diarahkan ke jalur pengambilan atau pemeriksaan yang berbeda?
A20: Catatan Penetapan Pembimbing | C20: Audit-DSIC-2906.pdf Data Berita wisata khusus jadesta (masih url): hasil_scraping_pertama_jadesta.xlsx Data Jadest zip data-jadesta.zip Audit terbaru: Protokol-dan-Teknis-Lab-DSIC-2906-1.pdf
A23: B. LOGBOOK 14 PERTEMUAN
A24: No | B24: Kode | C24: Tahap | D24: Fokus Pertemuan | E24: Tanggal | F24: Mode | G24: Durasi (menit) | H24: Yang Dilaporkan Mahasiswa | I24: Arahan & Catatan Pembimbing | J24: Target Pertemuan Berikutnya | K24: Link Artefak | L24: Status | M24: Verifikasi
A25: 1 | B25: P1 | C25: Bulan 1 | D25: Penetapan topik dan pertanyaan penelitian | E25: 46271 | F25: Luring | G25: 120 | I25: Silahkan di cari dataset multisumber yang sesuai dengan tourism indonesia | J25: 46276 | K25: https://github.com/Data-Systems-and-Intelligent-Computing/DSIC-2906 | L25: Selesai | M25: TRUE
A26: 2 | B26: P2 | C26: Bulan 1 | D26: Dataset, pembanding, dan ukuran keberhasilan | L26: Belum Dilaksanakan | M26: FALSE
A27: 3 | B27: P3 | C27: Bulan 1 | D27: Rencana eksperimen dan protokol pengukuran | L27: Belum Dilaksanakan | M27: FALSE
A28: 4 | B28: P4 | C28: Bulan 2 | D28: Hasil pembanding pertama | L28: Belum Dilaksanakan | M28: FALSE
A29: 5 | B29: P5 | C29: Bulan 2 | D29: Kesiapan data dan pipeline eksperimen | L29: Belum Dilaksanakan | M29: FALSE
A30: 6 | B30: P6 | C30: Bulan 2 | D30: Eksperimen utama, gelombang pertama | L30: Belum Dilaksanakan | M30: FALSE
A31: 7 | B31: P7 | C31: Bulan 3 | D31: Eksperimen utama, gelombang kedua | L31: Belum Dilaksanakan | M31: FALSE
A32: 8 | B32: P8 | C32: Bulan 3 | D32: Tinjauan hasil sementara dan koreksi arah | L32: Belum Dilaksanakan | M32: FALSE
A33: 9 | B33: P9 | C33: Bulan 3 | D33: Analisis hasil dan penyusunan tabel serta grafik | L33: Belum Dilaksanakan | M33: FALSE
A34: 10 | B34: P10 | C34: Bulan 4 | D34: Penutupan penelitian dan verifikasi keterulangan | L34: Belum Dilaksanakan | M34: FALSE
A35: 11 | B35: P11 | C35: Bulan 4 | D35: Kerangka naskah dan bab metode | L35: Belum Dilaksanakan | M35: FALSE
A36: 12 | B36: P12 | C36: Bulan 4 | D36: Bab hasil dan pembahasan | L36: Belum Dilaksanakan | M36: FALSE
A37: 13 | B37: P13 | C37: Bulan 4 | D37: Draf lengkap dan tinjauan menyeluruh | L37: Belum Dilaksanakan | M37: FALSE
A38: 14 | B38: P14 | C38: Bulan 4 | D38: Finalisasi dan kesiapan seminar atau sidang | L38: Belum Dilaksanakan | M38: FALSE
A41: C. CHECKLIST ARTEFAK MINIMUM
A42: No | B42: Artefak | C42: Link / Lokasi | D42: Selesai
A43: 1 | B43: Ringkasan masalah dan pertanyaan penelitian (1 halaman) | D43: FALSE
A44: 2 | B44: Daftar sumber dataset dan versi data | D44: FALSE
A45: 3 | B45: Kode atau notebook eksperimen | D45: FALSE
A46: 4 | B46: Catatan konfigurasi dan langkah menjalankan ulang | D46: FALSE
A47: 5 | B47: Hasil pembanding / baseline | D47: FALSE
A48: 6 | B48: Hasil eksperimen utama | D48: FALSE
A49: 7 | B49: Tabel atau grafik yang menjawab pertanyaan penelitian | D49: FALSE
A50: 8 | B50: Kesimpulan penelitian | D50: FALSE
A51: 9 | B51: Draf skripsi atau draf artikel ilmiah | D51: FALSE

Sheet 123450115
A1: LOGBOOK BIMBINGAN TUGAS AKHIR — DSIC RESEARCH GROUP
A2: NIM | C2: 123450115 | E2: Nama | G2: MUHAMMAD FADIL ALFAIZI
A3: Pertemuan selesai | C3: =COUNTIF(L25:L38,"Selesai") -> 2 | D3: Terverifikasi | F3: =COUNTIF(M25:M38,TRUE) -> 2 | G3: Progress | I3: =COUNTIF(L25:L38,"Selesai")/14 -> 0.14285714 | J3: Status topik | L3: =G5 -> Disetujui
A4: A. USULAN DAN PENETAPAN TOPIK
A5: Sumber Topik Final | C5: Katalog DSIC | E5: Status Topik | G5: Disetujui | I5: Tanggal Penetapan | K5: 46269
A6: Kode Topik Katalog | C6: DSIC29-07 | E6: Jalur Kelulusan | G6: Artikel Ilmiah | I6: Link Folder / Repo | K6: Drive / GitHub
A7: Judul dari Katalog | C7: {=IFERROR(INDEX(KATALOG_TOPIK!$D:$D,MATCH($C$6,KATALOG_TOPIK!$A:$A,0)),"")} -> Memilih Konfigurasi Sumber Daya Berdasarkan Jenis Beban
A8: Pertanyaan Penelitian Katalog | C8: {=IFERROR(INDEX(KATALOG_TOPIK!$E:$E,MATCH($C$6,KATALOG_TOPIK!$A:$A,0)),"")} -> Bisakah pengelompokan jenis beban kerja dipakai untuk memilih konfigurasi CPU dan memori yang lebih efisien?
A9: Dataset Katalog | C9: {=IFERROR(INDEX(KATALOG_TOPIK!$I:$I,MATCH($C$6,KATALOG_TOPIK!$A:$A,0)),"")} -> Kumpulan beban kerja standar yang dijalankan pada beberapa konfigurasi.
A10: Pembanding / Baseline Katalog | C10: {=IFERROR(INDEX(KATALOG_TOPIK!$G:$G,MATCH($C$6,KATALOG_TOPIK!$A:$A,0)),"")} -> Alokasi sumber daya tetap untuk semua beban.
A11: Kebaruan Katalog | C11: {=IFERROR(INDEX(KATALOG_TOPIK!$H:$H,MATCH($C$6,KATALOG_TOPIK!$A:$A,0)),"")} -> Pemilihan konfigurasi per jenis beban, diuji pada klaster kecil.
A12: Judul Usulan Mahasiswa | C12: Optimasi Komunikasi Asynchronous Federated Learning untuk Network Intrusion Detection melalui Demand-Aware Adaptive Resource Allocation pada Data Non-IID
A13: Pertanyaan Penelitian Usulan | C13: 1. Bagaimana karakteristik beban dan kondisi klien dapat dimanfaatkan untuk menentukan demand dan memilih konfigurasi sumber daya yang lebih efisien pada Federated Learning untuk NIDS?, 2. Sejauh mana demand-aware resource allocation dapat mengurangi biaya komunikasi dan komputasi dibandingkan alokasi tetap tanpa menurunkan kinerja deteksi NIDS secara signifikan pada data non-IID?
A14: Dataset Usulan | C14: UNSW-NB15
A15: Pembanding / Baseline Usulan | C15: Baseline: Menggunakan arsitektur FL asinkron, klien mengirimkan pembaruan model segera setelah local training selesai tanpa menunggu seluruh klien lain. Namun, alokasi sumber daya bersifat tetap/uniform: setiap klien menggunakan aturan yang sama untuk frekuensi partisipasi, ukuran/budget pembaruan model, dan komputasi lokal. Tidak terdapat mekanisme yang menyesuaikan resource berdasarkan karakteristik workload atau kondisi klien. Pembanding (Diusulkan): Menggunakan arsitektur FL asinkron yang sama dengan baseline, tetapi ditambahkan mekanisme demand estimation. Karakteristik workload dan kondisi masing-masing klien digunakan untuk menghitung kebutuhan (demand) pada waktu tertentu. Hasil estimasi tersebut kemudian digunakan untuk menentukan konfigurasi resource klien secara adaptif, yaitu frekuensi/prioritas partisipasi dan update budget. Contoh workload: jumlah sampel lokal klien, waktu local training terakhir, latency, throughput, staleness update klien terhadap global model, kontribusi update terhadap pembelajaran global. Contoh resource: Participation Frequency (prioritas klien untuk menghasilkan dan mengirim update dalam suatu interval pelatihan), Update Budget (batas maksimum informasi model yang diperbolehkan untuk dikirim oleh suatu klien dalam satu kontribusi, ukuran update). Lab yang digunakan: VPS/Cloud.
A16: Kebaruan / Gap Usulan | C16: Penelitian sebelumnya telah menggunakan komunikasi asinkron, tetapi keputusan komunikasi masih terutama berbentuk seleksi diterima/ditolak berdasarkan kriteria tertentu, bukan pemilihan konfigurasi resource komunikasi yang berbeda sesuai workload masing-masing klien. Penelitian ini mengusulkan mekanisme demand-aware resource allocation yang memetakan profil workload setiap klien menjadi konfigurasi resource berupa Participation Frequency dan Update Budget. Berbeda dengan baseline yang memberikan konfigurasi resource seragam kepada seluruh klien, metode usulan memungkinkan konfigurasi yang berbeda sesuai demand masing-masing klien. Kebaruan yang ditargetkan terletak pada evaluasi terkontrol mekanisme workload menjadi demand lalu memberikan FL resource configuration.
A17: Metrik Keberhasilan | C17: Metrik Keberhasilan: Keberhasilan dinilai dari efisiensi komunikasi/resource dan kinerja NIDS. Efisiensi komunikasi diukur menggunakan total data yang ditransmisikan (upload/download bytes), jumlah pembaruan model, rata-rata ukuran update, serta frekuensi partisipasi klien. Dampak terhadap komputasi diukur melalui jumlah local training executions, akumulasi waktu pelatihan lokal, dan time-to-target. Kinerja deteksi dinilai terutama menggunakan Macro-F1, attack recall, dan AUPRC, sedangkan Accuracy dan AUROC digunakan sebagai metrik sekunder untuk perbandingan dengan penelitian terdahulu. Metode Async + Demand-Aware dinyatakan berhasil apabila menghasilkan biaya komunikasi dan/atau komputasi yang lebih rendah dibandingkan Async dengan alokasi resource tetap, dengan performa deteksi yang tetap berada dalam batas toleransi/non-inferiority yang ditentukan sebelum eksperimen.
A18: Judul Final | C18: =IF($C$5="Katalog DSIC",$C$7,IF($C$5="Usulan Mahasiswa",$C$12,"")) -> Memilih Konfigurasi Sumber Daya Berdasarkan Jenis Beban
A19: Pertanyaan Penelitian Final | C19: =IF($C$5="Katalog DSIC",$C$8,IF($C$5="Usulan Mahasiswa",$C$13,"")) -> Bisakah pengelompokan jenis beban kerja dipakai untuk memilih konfigurasi CPU dan memori yang lebih efisien?
A20: Catatan Penetapan Pembimbing | C20: Audit-DSIC2907.pdf, Silahkan baca pustakan ini Resource-Aware Intelligent Communication Systems ( etc.) (z-library.sk, 1lib.sk, z-lib.sk).pdf, Berikut ini Revisi Audit dari saya Audit-DSIC-2907-Revisi.pdf
A23: B. LOGBOOK 14 PERTEMUAN
A24: No | B24: Kode | C24: Tahap | D24: Fokus Pertemuan | E24: Tanggal | F24: Mode | G24: Durasi (menit) | H24: Yang Dilaporkan Mahasiswa | I24: Arahan & Catatan Pembimbing | J24: Target Pertemuan Berikutnya | K24: Link Artefak | L24: Status | M24: Verifikasi
A25: 1 | B25: P1 | C25: Bulan 1 | D25: Penetapan topik dan pertanyaan penelitian | E25: 46269 | F25: Luring | G25: 2 jam | H25: Topik yang ditetapkan berkode DSIC29-07, "Memilih Konfigurasi Sumber Daya Berdasarkan Jenis Beban". Penelitian berfokus pada bagaimana karakteristik beban dan kondisi klien dapat dimanfaatkan untuk menentukan demand guna memilih konfigurasi sumber daya yang lebih efisien. | I25: Tambahkan lebih banyak pustaka artikel dan mulai menyusun draft artikelnya | J25: Dataset, pembanding, dan ukuran keberhasilan | K25: Drive | L25: Selesai | M25: TRUE
A26: 2 | B26: P2 | C26: Bulan 1 | D26: Dataset, pembanding, dan ukuran keberhasilan | E26: 46277 | F26: Luring | G26: 2 jam | H26: - Dataset, dilakukan pembagian validation 80/20. Preprocessing yang dilakukan berupa scaling, encoding, dan penyimpanan. Sebanyak 42 fitur sumber menjadi 192 fitur input model setelah encoding, artefak utama yang tersimpan berupa fitted-pipeline, indeks pembagian, nama fitur, konfigurasi, dan manifest. - Pembanding pertama adalah centralized MLP sanity baseline. Pembanding ini sebagai baseline untuk verifikasi preprocessing, fitur, metrik evaluasi, serta pipeline reproducibility. - Ukuran Keberhasilan berupa Macro-F1, Attack Recall, AUPRC / Average Precision, Accuracy, AUROC, Balanced Accuracy, dan Confusion Matrix. | I26: Perlu ada nya rencana kegiatan protokol dan lab, mulai ngelab minggu depan | J26: Dokumen protokol dan pertemuan di lab | K26: GitHub | L26: Selesai | M26: TRUE
A27: 3 | B27: P3 | C27: Bulan 1 | D27: Rencana eksperimen dan protokol pengukuran | L27: Belum Dilaksanakan | M27: FALSE
A28: 4 | B28: P4 | C28: Bulan 2 | D28: Hasil pembanding pertama | L28: Belum Dilaksanakan | M28: FALSE
A29: 5 | B29: P5 | C29: Bulan 2 | D29: Kesiapan data dan pipeline eksperimen | L29: Belum Dilaksanakan | M29: FALSE
A30: 6 | B30: P6 | C30: Bulan 2 | D30: Eksperimen utama, gelombang pertama | L30: Belum Dilaksanakan | M30: FALSE
A31: 7 | B31: P7 | C31: Bulan 3 | D31: Eksperimen utama, gelombang kedua | L31: Belum Dilaksanakan | M31: FALSE
A32: 8 | B32: P8 | C32: Bulan 3 | D32: Tinjauan hasil sementara dan koreksi arah | L32: Belum Dilaksanakan | M32: FALSE
A33: 9 | B33: P9 | C33: Bulan 3 | D33: Analisis hasil dan penyusunan tabel serta grafik | L33: Belum Dilaksanakan | M33: FALSE
A34: 10 | B34: P10 | C34: Bulan 4 | D34: Penutupan penelitian dan verifikasi keterulangan | L34: Belum Dilaksanakan | M34: FALSE
A35: 11 | B35: P11 | C35: Bulan 4 | D35: Kerangka naskah dan bab metode | L35: Belum Dilaksanakan | M35: FALSE
A36: 12 | B36: P12 | C36: Bulan 4 | D36: Bab hasil dan pembahasan | L36: Belum Dilaksanakan | M36: FALSE
A37: 13 | B37: P13 | C37: Bulan 4 | D37: Draf lengkap dan tinjauan menyeluruh | L37: Belum Dilaksanakan | M37: FALSE
A38: 14 | B38: P14 | C38: Bulan 4 | D38: Finalisasi dan kesiapan seminar atau sidang | L38: Belum Dilaksanakan | M38: FALSE
A41: C. CHECKLIST ARTEFAK MINIMUM
A42: No | B42: Artefak | C42: Link / Lokasi | D42: Selesai
A43: 1 | B43: Ringkasan masalah dan pertanyaan penelitian (1 halaman) | C43: Drive | D43: TRUE
A44: 2 | B44: Daftar sumber dataset dan versi data | D44: FALSE
A45: 3 | B45: Kode atau notebook eksperimen | D45: FALSE
A46: 4 | B46: Catatan konfigurasi dan langkah menjalankan ulang | D46: FALSE
A47: 5 | B47: Hasil pembanding / baseline | D47: FALSE
A48: 6 | B48: Hasil eksperimen utama | D48: FALSE
A49: 7 | B49: Tabel atau grafik yang menjawab pertanyaan penelitian | D49: FALSE
A50: 8 | B50: Kesimpulan penelitian | D50: FALSE
A51: 9 | B51: Draf skripsi atau draf artikel ilmiah | D51: FALSE

Sheet 123450003
A1: LOGBOOK BIMBINGAN TUGAS AKHIR — DSIC RESEARCH GROUP
A2: NIM | C2: 123450003 | E2: Nama | G2: Rahma Oktavia Albar
A3: Pertemuan selesai | C3: =COUNTIF(L25:L38,"Selesai") -> 0 | D3: Terverifikasi | F3: =COUNTIF(M25:M38,TRUE) -> 0 | G3: Progress | I3: =COUNTIF(L25:L38,"Selesai")/14 -> 0 | J3: Status topik | L3: =G5
A4: A. USULAN DAN PENETAPAN TOPIK
A5: Sumber Topik Final | C5: Usulan Mahasiswa | E5: Status Topik | I5: Tanggal Penetapan
A6: Kode Topik Katalog | E6: Jalur Kelulusan | I6: Link Folder / Repo
A7: Judul dari Katalog | C7: {=IFERROR(INDEX(KATALOG_TOPIK!$D:$D,MATCH($C$6,KATALOG_TOPIK!$A:$A,0)),"")}
A8: Pertanyaan Penelitian Katalog | C8: {=IFERROR(INDEX(KATALOG_TOPIK!$E:$E,MATCH($C$6,KATALOG_TOPIK!$A:$A,0)),"")}
A9: Dataset Katalog | C9: {=IFERROR(INDEX(KATALOG_TOPIK!$I:$I,MATCH($C$6,KATALOG_TOPIK!$A:$A,0)),"")}
A10: Pembanding / Baseline Katalog | C10: {=IFERROR(INDEX(KATALOG_TOPIK!$G:$G,MATCH($C$6,KATALOG_TOPIK!$A:$A,0)),"")}
A11: Kebaruan Katalog | C11: {=IFERROR(INDEX(KATALOG_TOPIK!$H:$H,MATCH($C$6,KATALOG_TOPIK!$A:$A,0)),"")}
A12: Judul Usulan Mahasiswa | C12: Ide 1 (Utama) : Pengembangan Sistem Pendukung Keputusan dan Rekomendasi Pemilihan Supplier Green Bean Kopi atau Komoditas Lain Melalui Metode Pengambilan Keputusan Multikriteria.
A13: Pertanyaan Penelitian Usulan
A14: Dataset Usulan
A15: Pembanding / Baseline Usulan
A16: Kebaruan / Gap Usulan
A17: Metrik Keberhasilan
A18: Judul Final | C18: =IF($C$5="Katalog DSIC",$C$7,IF($C$5="Usulan Mahasiswa",$C$12,"")) -> Ide 1 (Utama) : Pengembangan Sistem Pendukung Keputusan dan Rekomendasi Pemilihan Supplier Green Bean Kopi atau Komoditas Lain Melalui Metode Pengambilan Keputusan Multikriteria.
A19: Pertanyaan Penelitian Final | C19: =IF($C$5="Katalog DSIC",$C$8,IF($C$5="Usulan Mahasiswa",$C$13,""))
A20: Catatan Penetapan Pembimbing
A23: B. LOGBOOK 14 PERTEMUAN
A24: No | B24: Kode | C24: Tahap | D24: Fokus Pertemuan | E24: Tanggal | F24: Mode | G24: Durasi (menit) | H24: Yang Dilaporkan Mahasiswa | I24: Arahan & Catatan Pembimbing | J24: Target Pertemuan Berikutnya | K24: Link Artefak | L24: Status | M24: Verifikasi
A25: 1 | B25: P1 | C25: Bulan 1 | D25: Penetapan topik dan pertanyaan penelitian | L25: Belum Dilaksanakan | M25: FALSE
A26: 2 | B26: P2 | C26: Bulan 1 | D26: Dataset, pembanding, dan ukuran keberhasilan | L26: Belum Dilaksanakan | M26: FALSE
A27: 3 | B27: P3 | C27: Bulan 1 | D27: Rencana eksperimen dan protokol pengukuran | L27: Belum Dilaksanakan | M27: FALSE
A28: 4 | B28: P4 | C28: Bulan 2 | D28: Hasil pembanding pertama | L28: Belum Dilaksanakan | M28: FALSE
A29: 5 | B29: P5 | C29: Bulan 2 | D29: Kesiapan data dan pipeline eksperimen | L29: Belum Dilaksanakan | M29: FALSE
A30: 6 | B30: P6 | C30: Bulan 2 | D30: Eksperimen utama, gelombang pertama | L30: Belum Dilaksanakan | M30: FALSE
A31: 7 | B31: P7 | C31: Bulan 3 | D31: Eksperimen utama, gelombang kedua | L31: Belum Dilaksanakan | M31: FALSE
A32: 8 | B32: P8 | C32: Bulan 3 | D32: Tinjauan hasil sementara dan koreksi arah | L32: Belum Dilaksanakan | M32: FALSE
A33: 9 | B33: P9 | C33: Bulan 3 | D33: Analisis hasil dan penyusunan tabel serta grafik | L33: Belum Dilaksanakan | M33: FALSE
A34: 10 | B34: P10 | C34: Bulan 4 | D34: Penutupan penelitian dan verifikasi keterulangan | L34: Belum Dilaksanakan | M34: FALSE
A35: 11 | B35: P11 | C35: Bulan 4 | D35: Kerangka naskah dan bab metode | L35: Belum Dilaksanakan | M35: FALSE
A36: 12 | B36: P12 | C36: Bulan 4 | D36: Bab hasil dan pembahasan | L36: Belum Dilaksanakan | M36: FALSE
... A38: 14 | B38: P14 | C38: Bulan 4 | D38: Finalisasi dan kesiapan seminar atau sidang | L38: Belum Dilaksanakan | M38: FALSE
A41: C. CHECKLIST ARTEFAK MINIMUM
A42: No | B42: Artefak | C42: Link / Lokasi | D42: Selesai
A43: 1 | B43: Ringkasan masalah dan pertanyaan penelitian (1 halaman) | D43: FALSE
A44: 2 | B44: Daftar sumber dataset dan versi data | D44: FALSE
A45: 3 | B45: Kode atau notebook eksperimen | D45: FALSE
A46: 4 | B46: Catatan konfigurasi dan langkah menjalankan ulang | D46: FALSE
A47: 5 | B47: Hasil pembanding / baseline | D47: FALSE
A48: 6 | B48: Hasil eksperimen utama | D48: FALSE
A49: 7 | B49: Tabel atau grafik yang menjawab pertanyaan penelitian | D49: FALSE
A50: 8 | B50: Kesimpulan penelitian | D50: FALSE
A51: 9 | B51: Draf skripsi atau draf artikel ilmiah | D51: FALSE

Sheet 123450029
A1: LOGBOOK BIMBINGAN TUGAS AKHIR — DSIC RESEARCH GROUP
A2: NIM | C2: 123450029 | E2: Nama | G2: Vania Claresta
A3: Pertemuan selesai | C3: =COUNTIF(L25:L38,"Selesai") -> 1 | D3: Terverifikasi | F3: =COUNTIF(M25:M38,TRUE) -> 1 | G3: Progress | I3: =COUNTIF(L25:L38,"Selesai")/14 -> 0.071428571 | J3: Status topik | L3: =G5 -> Disetujui
A4: A. USULAN DAN PENETAPAN TOPIK
A5: Sumber Topik Final | C5: Katalog DSIC | E5: Status Topik | G5: Disetujui | I5: Tanggal Penetapan | K5: 46272
A6: Kode Topik Katalog | C6: DSIC26-06 | E6: Jalur Kelulusan | G6: Skripsi Tradisional | I6: Link Folder / Repo | K6: https://drive.google.com/drive/folders/1YQpC-qrSoNSdYwWGwNnavDKfWM3HWs3f?usp=sharing
A7: Judul dari Katalog | C7: {=IFERROR(INDEX(KATALOG_TOPIK!$D:$D,MATCH($C$6,KATALOG_TOPIK!$A:$A,0)),"")} -> Apa yang Terjadi Ketika Pipeline Gagal di Tengah Jalan?
A8: Pertanyaan Penelitian Katalog | C8: {=IFERROR(INDEX(KATALOG_TOPIK!$E:$E,MATCH($C$6,KATALOG_TOPIK!$A:$A,0)),"")} -> Bagaimana kombinasi pengulangan, titik simpan, dan operasi yang aman diulang memengaruhi kebenaran data ketika satu pekerja gagal di tengah proses pemasukan data?
A9: Dataset Katalog | C9: {=IFERROR(INDEX(KATALOG_TOPIK!$I:$I,MATCH($C$6,KATALOG_TOPIK!$A:$A,0)),"")} -> NYC TLC atau snapshot JADESTA yang dialirkan bertahap, dengan kegagalan yang sengaja dipicu pada titik-titik tertentu.
A10: Pembanding / Baseline Katalog | C10: {=IFERROR(INDEX(KATALOG_TOPIK!$G:$G,MATCH($C$6,KATALOG_TOPIK!$A:$A,0)),"")} -> Pengulangan sederhana bergaya at-least-once.
A11: Kebaruan Katalog | C11: {=IFERROR(INDEX(KATALOG_TOPIK!$H:$H,MATCH($C$6,KATALOG_TOPIK!$A:$A,0)),"")} -> Yang diukur adalah kebenaran data setelah pemulihan, bukan sekadar berapa lama sistem kembali menyala.
A12: Judul Usulan Mahasiswa | C12: Correctness Data Pasca-Pemulihan pada Checkpointing dan Idempotent Ingestion di Pipeline AudioMoth Berbasis Objek
A13: Pertanyaan Penelitian Usulan | C13: Bagaimana checkpointing dan idempotent ingestion memengaruhi kebenaran data setelah kegagalan pekerja pada pipeline ingestion AudioMoth, ditinjau dari kehilangan rekaman, duplikasi, dan konsistensi antara objek audio dan metadata?
A14: Dataset Usulan | C14: Korpus rekaman WAV AudioMoth yang dibekukan sebagai ground-truth dataset. Setiap rekaman dilengkapi manifest minimal berupa recording_id, device_id, start_time, file_size, object_uri, dan SHA-256. Data direplay secara bertahap sebagai micro-batch ingestion menuju object storage.
A15: Pembanding / Baseline Usulan | C15: Retry at-least-once tanpa checkpoint persisten dan tanpa idempotent ingestion sebagai baseline. Dibandingkan dengan: (1) checkpoint saja, (2) idempotent ingestion saja, dan (3) checkpoint + idempotent ingestion.
A16: Kebaruan / Gap Usulan | C16: Mengevaluasi post-recovery data correctness pada pipeline bioakustik berbasis objek, bukan hanya waktu pemulihan sistem. Evaluasi mencakup konsistensi dua state—WAV object dan metadata manifest—ketika kegagalan terjadi pada titik berbeda dalam pipeline. Posisi ini merupakan gap penelitian yang diusulkan dan masih harus divalidasi melalui kajian literatur sebelum diklaim sebagai kebaruan ilmiah.
A17: Metrik Keberhasilan | C17: Missing recording rate, duplicate recording rate, orphan object count (WAV ada, metadata tidak ada), dangling metadata count (metadata ada, WAV tidak ada), checksum mismatch, exact recovery rate, jumlah/bytes data yang diproses ulang, serta recovery time.
A18: Judul Final | C18: =IF($C$5="Katalog DSIC",$C$7,IF($C$5="Usulan Mahasiswa",$C$12,"")) -> Apa yang Terjadi Ketika Pipeline Gagal di Tengah Jalan?
A19: Pertanyaan Penelitian Final | C19: =IF($C$5="Katalog DSIC",$C$8,IF($C$5="Usulan Mahasiswa",$C$13,"")) -> Bagaimana kombinasi pengulangan, titik simpan, dan operasi yang aman diulang memengaruhi kebenaran data ketika satu pekerja gagal di tengah proses pemasukan data?
A20: Catatan Penetapan Pembimbing | C20: Menggunakan dataset dari Audiomoth, berikut audit topik: Audit-DSIC-2606-Checkpointing-Idempotent-AudioMoth-Ingestion.pdf Protokol Lab: Protokol-dan-Teknis-Lab-DSIC-2606.pdf
A23: B. LOGBOOK 14 PERTEMUAN
A24: No | B24: Kode | C24: Tahap | D24: Fokus Pertemuan | E24: Tanggal | F24: Mode | G24: Durasi (menit) | H24: Yang Dilaporkan Mahasiswa | I24: Arahan & Catatan Pembimbing | J24: Target Pertemuan Berikutnya | K24: Link Artefak | L24: Status | M24: Verifikasi
A25: 1 | B25: P1 | C25: Bulan 1 | D25: Penetapan topik dan pertanyaan penelitian | E25: 46274 | F25: Luring | H25: Mencari jurnal untuk menemukan referensi gap antara penelitian terdahulu | L25: Selesai | M25: TRUE
A26: 2 | B26: P2 | C26: Bulan 1 | D26: Dataset, pembanding, dan ukuran keberhasilan | L26: Belum Dilaksanakan | M26: FALSE
A27: 3 | B27: P3 | C27: Bulan 1 | D27: Rencana eksperimen dan protokol pengukuran | L27: Belum Dilaksanakan | M27: FALSE
A28: 4 | B28: P4 | C28: Bulan 2 | D28: Hasil pembanding pertama | L28: Belum Dilaksanakan | M28: FALSE
A29: 5 | B29: P5 | C29: Bulan 2 | D29: Kesiapan data dan pipeline eksperimen | L29: Belum Dilaksanakan | M29: FALSE
A30: 6 | B30: P6 | C30: Bulan 2 | D30: Eksperimen utama, gelombang pertama | L30: Belum Dilaksanakan | M30: FALSE
A31: 7 | B31: P7 | C31: Bulan 3 | D31: Eksperimen utama, gelombang kedua | L31: Belum Dilaksanakan | M31: FALSE
A32: 8 | B32: P8 | C32: Bulan 3 | D32: Tinjauan hasil sementara dan koreksi arah | L32: Belum Dilaksanakan | M32: FALSE
A33: 9 | B33: P9 | C33: Bulan 3 | D33: Analisis hasil dan penyusunan tabel serta grafik | L33: Belum Dilaksanakan | M33: FALSE
A34: 10 | B34: P10 | C34: Bulan 4 | D34: Penutupan penelitian dan verifikasi keterulangan | L34: Belum Dilaksanakan | M34: FALSE
A35: 11 | B35: P11 | C35: Bulan 4 | D35: Kerangka naskah dan bab metode | L35: Belum Dilaksanakan | M35: FALSE
A36: 12 | B36: P12 | C36: Bulan 4 | D36: Bab hasil dan pembahasan | L36: Belum Dilaksanakan | M36: FALSE
A37: 13 | B37: P13 | C37: Bulan 4 | D37: Draf lengkap dan tinjauan menyeluruh | L37: Belum Dilaksanakan | M37: FALSE
A38: 14 | B38: P14 | C38: Bulan 4 | D38: Finalisasi dan kesiapan seminar atau sidang | L38: Belum Dilaksanakan | M38: FALSE
A41: C. CHECKLIST ARTEFAK MINIMUM
A42: No | B42: Artefak | C42: Link / Lokasi | D42: Selesai
A43: 1 | B43: Ringkasan masalah dan pertanyaan penelitian (1 halaman) | D43: FALSE
A44: 2 | B44: Daftar sumber dataset dan versi data | D44: FALSE
A45: 3 | B45: Kode atau notebook eksperimen | D45: FALSE
A46: 4 | B46: Catatan konfigurasi dan langkah menjalankan ulang | D46: FALSE
A47: 5 | B47: Hasil pembanding / baseline | D47: FALSE
A48: 6 | B48: Hasil eksperimen utama | D48: FALSE
A49: 7 | B49: Tabel atau grafik yang menjawab pertanyaan penelitian | D49: FALSE
A50: 8 | B50: Kesimpulan penelitian | D50: FALSE
A51: 9 | B51: Draf skripsi atau draf artikel ilmiah | D51: FALSE
